{
  "schema_version": 1,
  "meta": {
    "flight_number": null,
    "callsign": "DLH67K",
    "icao24": "3c6487",
    "date": "2026-06-25",
    "source": "opensky-rest-tracks",
    "generated_at": "2026-06-27T21:22:29Z"
  },
  "origin": {
    "icao": "EDDF",
    "iata": null,
    "name": null,
    "lat": 50.0159,
    "lon": 8.5261
  },
  "destination": {
    "icao": "LEMD",
    "iata": null,
    "name": null,
    "lat": 40.4642,
    "lon": -3.5266
  },
  "waypoints": [
    {
      "t": 1782421081,
      "t_rel": 0.0,
      "lat": 50.0159,
      "lon": 8.5261,
      "alt_m": 0.0,
      "heading_deg": 180.0,
      "speed_mps": 94.25155218229003,
      "on_ground": false
    },
    {
      "t": 1782421102,
      "t_rel": 21.0,
      "lat": 49.9981,
      "lon": 8.5262,
      "alt_m": 304.0,
      "heading_deg": 179.0,
      "speed_mps": 94.25155218229003,
      "on_ground": false
    },
    {
      "t": 1782421139,
      "t_rel": 58.0,
      "lat": 49.9655,
      "lon": 8.5286,
      "alt_m": 609.0,
      "heading_deg": 176.0,
      "speed_mps": 98.08146437547776,
      "on_ground": false
    },
    {
      "t": 1782421185,
      "t_rel": 104.0,
      "lat": 49.9168,
      "lon": 8.5322,
      "alt_m": 914.0,
      "heading_deg": 177.0,
      "speed_mps": 117.85473031129314,
      "on_ground": false
    },
    {
      "t": 1782421208,
      "t_rel": 127.0,
      "lat": 49.8914,
      "lon": 8.5339,
      "alt_m": 1219.0,
      "heading_deg": 177.0,
      "speed_mps": 122.91191473865665,
      "on_ground": false
    },
    {
      "t": 1782421231,
      "t_rel": 150.0,
      "lat": 49.8661,
      "lon": 8.5356,
      "alt_m": 1524.0,
      "heading_deg": 177.0,
      "speed_mps": 122.42902914265669,
      "on_ground": false
    },
    {
      "t": 1782421259,
      "t_rel": 178.0,
      "lat": 49.8351,
      "lon": 8.5376,
      "alt_m": 1828.0,
      "heading_deg": 177.0,
      "speed_mps": 123.21514054891297,
      "on_ground": false
    },
    {
      "t": 1782421285,
      "t_rel": 204.0,
      "lat": 49.8057,
      "lon": 8.5396,
      "alt_m": 1828.0,
      "heading_deg": 177.0,
      "speed_mps": 125.85684885556513,
      "on_ground": false
    },
    {
      "t": 1782421300,
      "t_rel": 219.0,
      "lat": 49.7886,
      "lon": 8.5408,
      "alt_m": 1828.0,
      "heading_deg": 177.0,
      "speed_mps": 126.89220164793538,
      "on_ground": false
    },
    {
      "t": 1782421306,
      "t_rel": 225.0,
      "lat": 49.7818,
      "lon": 8.5408,
      "alt_m": 1828.0,
      "heading_deg": 180.0,
      "speed_mps": 126.02091686393457,
      "on_ground": false
    },
    {
      "t": 1782421310,
      "t_rel": 229.0,
      "lat": 49.7773,
      "lon": 8.5405,
      "alt_m": 1828.0,
      "heading_deg": 182.0,
      "speed_mps": 125.21015051868184,
      "on_ground": false
    },
    {
      "t": 1782421312,
      "t_rel": 231.0,
      "lat": 49.775,
      "lon": 8.5402,
      "alt_m": 2438.0,
      "heading_deg": 184.0,
      "speed_mps": 128.32699501801875,
      "on_ground": false
    },
    {
      "t": 1782421313,
      "t_rel": 232.0,
      "lat": 49.7738,
      "lon": 8.5399,
      "alt_m": 2438.0,
      "heading_deg": 185.0,
      "speed_mps": 135.16176985203606,
      "on_ground": false
    },
    {
      "t": 1782421314,
      "t_rel": 233.0,
      "lat": 49.7727,
      "lon": 8.5396,
      "alt_m": 2438.0,
      "heading_deg": 187.0,
      "speed_mps": 124.19715923366724,
      "on_ground": false
    },
    {
      "t": 1782421315,
      "t_rel": 234.0,
      "lat": 49.7716,
      "lon": 8.5393,
      "alt_m": 2438.0,
      "heading_deg": 189.0,
      "speed_mps": 124.19724405120621,
      "on_ground": false
    },
    {
      "t": 1782421316,
      "t_rel": 235.0,
      "lat": 49.7703,
      "lon": 8.5388,
      "alt_m": 2438.0,
      "heading_deg": 190.0,
      "speed_mps": 148.94637819515418,
      "on_ground": false
    },
    {
      "t": 1782421317,
      "t_rel": 236.0,
      "lat": 49.7693,
      "lon": 8.5384,
      "alt_m": 2438.0,
      "heading_deg": 192.0,
      "speed_mps": 114.84566344237284,
      "on_ground": false
    },
    {
      "t": 1782421318,
      "t_rel": 237.0,
      "lat": 49.7682,
      "lon": 8.5378,
      "alt_m": 2438.0,
      "heading_deg": 194.0,
      "speed_mps": 129.68280799664424,
      "on_ground": false
    },
    {
      "t": 1782421319,
      "t_rel": 238.0,
      "lat": 49.7671,
      "lon": 8.5373,
      "alt_m": 2438.0,
      "heading_deg": 196.0,
      "speed_mps": 127.47678034796535,
      "on_ground": false
    },
    {
      "t": 1782421320,
      "t_rel": 239.0,
      "lat": 49.7661,
      "lon": 8.5367,
      "alt_m": 2438.0,
      "heading_deg": 197.0,
      "speed_mps": 119.2530500672803,
      "on_ground": false
    },
    {
      "t": 1782421321,
      "t_rel": 240.0,
      "lat": 49.765,
      "lon": 8.5361,
      "alt_m": 2438.0,
      "heading_deg": 199.0,
      "speed_mps": 129.68375324282866,
      "on_ground": false
    },
    {
      "t": 1782421322,
      "t_rel": 241.0,
      "lat": 49.7636,
      "lon": 8.5351,
      "alt_m": 2438.0,
      "heading_deg": 200.0,
      "speed_mps": 171.44332394092658,
      "on_ground": false
    },
    {
      "t": 1782421323,
      "t_rel": 242.0,
      "lat": 49.7626,
      "lon": 8.5344,
      "alt_m": 2438.0,
      "heading_deg": 202.0,
      "speed_mps": 122.03372653356094,
      "on_ground": false
    },
    {
      "t": 1782421324,
      "t_rel": 243.0,
      "lat": 49.7614,
      "lon": 8.5336,
      "alt_m": 2438.0,
      "heading_deg": 204.0,
      "speed_mps": 145.28086610106786,
      "on_ground": false
    },
    {
      "t": 1782421325,
      "t_rel": 244.0,
      "lat": 49.7608,
      "lon": 8.533,
      "alt_m": 2438.0,
      "heading_deg": 205.0,
      "speed_mps": 79.42639259778737,
      "on_ground": false
    },
    {
      "t": 1782421327,
      "t_rel": 246.0,
      "lat": 49.7582,
      "lon": 8.531,
      "alt_m": 2438.0,
      "heading_deg": 206.0,
      "speed_mps": 161.41707069411132,
      "on_ground": false
    },
    {
      "t": 1782421359,
      "t_rel": 278.0,
      "lat": 49.722,
      "lon": 8.5008,
      "alt_m": 2743.0,
      "heading_deg": 208.0,
      "speed_mps": 142.9064344062283,
      "on_ground": false
    },
    {
      "t": 1782421387,
      "t_rel": 306.0,
      "lat": 49.6882,
      "lon": 8.4726,
      "alt_m": 3048.0,
      "heading_deg": 208.0,
      "speed_mps": 152.52115417579358,
      "on_ground": false
    },
    {
      "t": 1782421417,
      "t_rel": 336.0,
      "lat": 49.6518,
      "lon": 8.4422,
      "alt_m": 3352.0,
      "heading_deg": 208.0,
      "speed_mps": 153.36337177945745,
      "on_ground": false
    },
    {
      "t": 1782421475,
      "t_rel": 394.0,
      "lat": 49.5725,
      "lon": 8.3762,
      "alt_m": 3657.0,
      "heading_deg": 208.0,
      "speed_mps": 172.7286020443328,
      "on_ground": false
    },
    {
      "t": 1782421541,
      "t_rel": 460.0,
      "lat": 49.4693,
      "lon": 8.2907,
      "alt_m": 3962.0,
      "heading_deg": 208.0,
      "speed_mps": 197.42000583141845,
      "on_ground": false
    },
    {
      "t": 1782421588,
      "t_rel": 507.0,
      "lat": 49.3887,
      "lon": 8.224,
      "alt_m": 3962.0,
      "heading_deg": 208.0,
      "speed_mps": 216.5530379670821,
      "on_ground": false
    },
    {
      "t": 1782421619,
      "t_rel": 538.0,
      "lat": 49.3345,
      "lon": 8.1793,
      "alt_m": 4572.0,
      "heading_deg": 208.0,
      "speed_mps": 220.68147762003574,
      "on_ground": false
    },
    {
      "t": 1782421652,
      "t_rel": 571.0,
      "lat": 49.2762,
      "lon": 8.1314,
      "alt_m": 4876.0,
      "heading_deg": 208.0,
      "speed_mps": 222.85739696520628,
      "on_ground": false
    },
    {
      "t": 1782421695,
      "t_rel": 614.0,
      "lat": 49.1988,
      "lon": 8.0681,
      "alt_m": 5181.0,
      "heading_deg": 208.0,
      "speed_mps": 226.8986903391103,
      "on_ground": false
    },
    {
      "t": 1782421736,
      "t_rel": 655.0,
      "lat": 49.1246,
      "lon": 8.0076,
      "alt_m": 5486.0,
      "heading_deg": 208.0,
      "speed_mps": 228.05334528711785,
      "on_ground": false
    },
    {
      "t": 1782421773,
      "t_rel": 692.0,
      "lat": 49.056,
      "lon": 7.9519,
      "alt_m": 5791.0,
      "heading_deg": 207.0,
      "speed_mps": 233.493518650932,
      "on_ground": false
    },
    {
      "t": 1782421826,
      "t_rel": 745.0,
      "lat": 48.957,
      "lon": 7.8718,
      "alt_m": 6096.0,
      "heading_deg": 207.0,
      "speed_mps": 235.14473398433486,
      "on_ground": false
    },
    {
      "t": 1782421879,
      "t_rel": 798.0,
      "lat": 48.8555,
      "lon": 7.7901,
      "alt_m": 6400.0,
      "heading_deg": 207.0,
      "speed_mps": 240.9162380457275,
      "on_ground": false
    },
    {
      "t": 1782421926,
      "t_rel": 845.0,
      "lat": 48.7645,
      "lon": 7.7171,
      "alt_m": 6705.0,
      "heading_deg": 207.0,
      "speed_mps": 243.4892309009255,
      "on_ground": false
    },
    {
      "t": 1782421981,
      "t_rel": 900.0,
      "lat": 48.6562,
      "lon": 7.6307,
      "alt_m": 7010.0,
      "heading_deg": 207.0,
      "speed_mps": 247.43894361776628,
      "on_ground": false
    },
    {
      "t": 1782422036,
      "t_rel": 955.0,
      "lat": 48.5474,
      "lon": 7.5444,
      "alt_m": 7315.0,
      "heading_deg": 207.0,
      "speed_mps": 248.38716420092234,
      "on_ground": false
    },
    {
      "t": 1782422096,
      "t_rel": 1015.0,
      "lat": 48.4269,
      "lon": 7.449,
      "alt_m": 7620.0,
      "heading_deg": 207.0,
      "speed_mps": 252.1935376074576,
      "on_ground": false
    },
    {
      "t": 1782422148,
      "t_rel": 1067.0,
      "lat": 48.3228,
      "lon": 7.3672,
      "alt_m": 7924.0,
      "heading_deg": 207.0,
      "speed_mps": 251.1026444471134,
      "on_ground": false
    },
    {
      "t": 1782422202,
      "t_rel": 1121.0,
      "lat": 48.2149,
      "lon": 7.2827,
      "alt_m": 8229.0,
      "heading_deg": 207.0,
      "speed_mps": 250.55944015650198,
      "on_ground": false
    },
    {
      "t": 1782422249,
      "t_rel": 1168.0,
      "lat": 48.1215,
      "lon": 7.21,
      "alt_m": 8229.0,
      "heading_deg": 207.0,
      "speed_mps": 248.97174196724143,
      "on_ground": false
    },
    {
      "t": 1782422301,
      "t_rel": 1220.0,
      "lat": 48.0195,
      "lon": 7.131,
      "alt_m": 8839.0,
      "heading_deg": 207.0,
      "speed_mps": 245.59255925964558,
      "on_ground": false
    },
    {
      "t": 1782422358,
      "t_rel": 1277.0,
      "lat": 47.9075,
      "lon": 7.0446,
      "alt_m": 9144.0,
      "heading_deg": 207.0,
      "speed_mps": 245.91582054287764,
      "on_ground": false
    },
    {
      "t": 1782422422,
      "t_rel": 1341.0,
      "lat": 47.7821,
      "lon": 6.9481,
      "alt_m": 9448.0,
      "heading_deg": 207.0,
      "speed_mps": 245.21447062843657,
      "on_ground": false
    },
    {
      "t": 1782422471,
      "t_rel": 1390.0,
      "lat": 47.6865,
      "lon": 6.8751,
      "alt_m": 9753.0,
      "heading_deg": 207.0,
      "speed_mps": 243.88133544223828,
      "on_ground": false
    },
    {
      "t": 1782422521,
      "t_rel": 1440.0,
      "lat": 47.5929,
      "lon": 6.8039,
      "alt_m": 10058.0,
      "heading_deg": 207.0,
      "speed_mps": 233.90561925367336,
      "on_ground": false
    },
    {
      "t": 1782422601,
      "t_rel": 1520.0,
      "lat": 47.443,
      "lon": 6.69,
      "alt_m": 10058.0,
      "heading_deg": 208.0,
      "speed_mps": 234.1835049328382,
      "on_ground": false
    },
    {
      "t": 1782422614,
      "t_rel": 1533.0,
      "lat": 47.4194,
      "lon": 6.6699,
      "alt_m": 10363.0,
      "heading_deg": 210.0,
      "speed_mps": 232.96863423315386,
      "on_ground": false
    },
    {
      "t": 1782422699,
      "t_rel": 1618.0,
      "lat": 47.2667,
      "lon": 6.5325,
      "alt_m": 10363.0,
      "heading_deg": 212.0,
      "speed_mps": 233.96046198622403,
      "on_ground": false
    },
    {
      "t": 1782422709,
      "t_rel": 1628.0,
      "lat": 47.2496,
      "lon": 6.5157,
      "alt_m": 10363.0,
      "heading_deg": 214.0,
      "speed_mps": 228.53677291284345,
      "on_ground": false
    },
    {
      "t": 1782422719,
      "t_rel": 1638.0,
      "lat": 47.2327,
      "lon": 6.4975,
      "alt_m": 10668.0,
      "heading_deg": 217.0,
      "speed_mps": 232.7898668601627,
      "on_ground": false
    },
    {
      "t": 1782422720,
      "t_rel": 1639.0,
      "lat": 47.2312,
      "lon": 6.4957,
      "alt_m": 10363.0,
      "heading_deg": 217.0,
      "speed_mps": 215.15324264409773,
      "on_ground": false
    },
    {
      "t": 1782422721,
      "t_rel": 1640.0,
      "lat": 47.2298,
      "lon": 6.4941,
      "alt_m": 10668.0,
      "heading_deg": 217.0,
      "speed_mps": 197.05174695209732,
      "on_ground": false
    },
    {
      "t": 1782422724,
      "t_rel": 1643.0,
      "lat": 47.2241,
      "lon": 6.4876,
      "alt_m": 10668.0,
      "heading_deg": 218.0,
      "speed_mps": 267.2137885337349,
      "on_ground": false
    },
    {
      "t": 1782422908,
      "t_rel": 1827.0,
      "lat": 46.9283,
      "lon": 6.1183,
      "alt_m": 10363.0,
      "heading_deg": 220.0,
      "speed_mps": 234.6369690082713,
      "on_ground": false
    },
    {
      "t": 1782422909,
      "t_rel": 1828.0,
      "lat": 46.9265,
      "lon": 6.1161,
      "alt_m": 10668.0,
      "heading_deg": 220.0,
      "speed_mps": 260.71138530885486,
      "on_ground": false
    },
    {
      "t": 1782422914,
      "t_rel": 1833.0,
      "lat": 46.9187,
      "lon": 6.1063,
      "alt_m": 10363.0,
      "heading_deg": 220.0,
      "speed_mps": 228.57493613351886,
      "on_ground": false
    },
    {
      "t": 1782422915,
      "t_rel": 1834.0,
      "lat": 46.9176,
      "lon": 6.105,
      "alt_m": 10668.0,
      "heading_deg": 220.0,
      "speed_mps": 157.19299172245235,
      "on_ground": false
    },
    {
      "t": 1782422917,
      "t_rel": 1836.0,
      "lat": 46.9139,
      "lon": 6.1004,
      "alt_m": 10363.0,
      "heading_deg": 220.0,
      "speed_mps": 269.8798361120091,
      "on_ground": false
    },
    {
      "t": 1782422918,
      "t_rel": 1837.0,
      "lat": 46.9129,
      "lon": 6.0992,
      "alt_m": 10668.0,
      "heading_deg": 220.0,
      "speed_mps": 143.77924359087874,
      "on_ground": false
    },
    {
      "t": 1782423001,
      "t_rel": 1920.0,
      "lat": 46.7797,
      "lon": 5.9346,
      "alt_m": 10363.0,
      "heading_deg": 220.0,
      "speed_mps": 233.6470953466471,
      "on_ground": false
    },
    {
      "t": 1782423002,
      "t_rel": 1921.0,
      "lat": 46.7781,
      "lon": 5.9326,
      "alt_m": 10668.0,
      "heading_deg": 220.0,
      "speed_mps": 234.1937576258662,
      "on_ground": false
    },
    {
      "t": 1782423004,
      "t_rel": 1923.0,
      "lat": 46.7744,
      "lon": 5.9281,
      "alt_m": 10363.0,
      "heading_deg": 220.0,
      "speed_mps": 267.7214063454812,
      "on_ground": false
    },
    {
      "t": 1782423006,
      "t_rel": 1925.0,
      "lat": 46.7714,
      "lon": 5.9243,
      "alt_m": 10668.0,
      "heading_deg": 220.0,
      "speed_mps": 220.80992289811266,
      "on_ground": false
    },
    {
      "t": 1782423007,
      "t_rel": 1926.0,
      "lat": 46.7696,
      "lon": 5.9222,
      "alt_m": 10363.0,
      "heading_deg": 220.0,
      "speed_mps": 256.20269273803774,
      "on_ground": false
    },
    {
      "t": 1782423009,
      "t_rel": 1928.0,
      "lat": 46.7664,
      "lon": 5.9182,
      "alt_m": 10668.0,
      "heading_deg": 220.0,
      "speed_mps": 234.21380585985293,
      "on_ground": false
    },
    {
      "t": 1782423010,
      "t_rel": 1929.0,
      "lat": 46.7646,
      "lon": 5.916,
      "alt_m": 10363.0,
      "heading_deg": 220.0,
      "speed_mps": 261.03481281209565,
      "on_ground": false
    },
    {
      "t": 1782423011,
      "t_rel": 1930.0,
      "lat": 46.7638,
      "lon": 5.915,
      "alt_m": 10668.0,
      "heading_deg": 220.0,
      "speed_mps": 117.11039747011417,
      "on_ground": false
    },
    {
      "t": 1782423017,
      "t_rel": 1936.0,
      "lat": 46.7534,
      "lon": 5.9022,
      "alt_m": 10363.0,
      "heading_deg": 220.0,
      "speed_mps": 252.10611454758853,
      "on_ground": false
    },
    {
      "t": 1782423018,
      "t_rel": 1937.0,
      "lat": 46.7524,
      "lon": 5.9011,
      "alt_m": 10668.0,
      "heading_deg": 220.0,
      "speed_mps": 139.2382722402637,
      "on_ground": false
    },
    {
      "t": 1782423019,
      "t_rel": 1938.0,
      "lat": 46.7508,
      "lon": 5.8991,
      "alt_m": 10363.0,
      "heading_deg": 220.0,
      "speed_mps": 234.24396795538985,
      "on_ground": false
    },
    {
      "t": 1782423020,
      "t_rel": 1939.0,
      "lat": 46.7485,
      "lon": 5.8963,
      "alt_m": 10668.0,
      "heading_deg": 220.0,
      "speed_mps": 333.0420319431269,
      "on_ground": false
    },
    {
      "t": 1782423021,
      "t_rel": 1940.0,
      "lat": 46.747,
      "lon": 5.8943,
      "alt_m": 10363.0,
      "heading_deg": 220.0,
      "speed_mps": 225.92170543289458,
      "on_ground": false
    },
    {
      "t": 1782423022,
      "t_rel": 1941.0,
      "lat": 46.7457,
      "lon": 5.8927,
      "alt_m": 10668.0,
      "heading_deg": 220.0,
      "speed_mps": 189.09744784659622,
      "on_ground": false
    },
    {
      "t": 1782423024,
      "t_rel": 1943.0,
      "lat": 46.7424,
      "lon": 5.8888,
      "alt_m": 10363.0,
      "heading_deg": 220.0,
      "speed_mps": 236.0916178394958,
      "on_ground": false
    },
    {
      "t": 1782423028,
      "t_rel": 1947.0,
      "lat": 46.7362,
      "lon": 5.8811,
      "alt_m": 10668.0,
      "heading_deg": 220.0,
      "speed_mps": 226.3272074421976,
      "on_ground": false
    },
    {
      "t": 1782423033,
      "t_rel": 1952.0,
      "lat": 46.7285,
      "lon": 5.8716,
      "alt_m": 10363.0,
      "heading_deg": 220.0,
      "speed_mps": 224.25889682610378,
      "on_ground": false
    },
    {
      "t": 1782423035,
      "t_rel": 1954.0,
      "lat": 46.7245,
      "lon": 5.8667,
      "alt_m": 10668.0,
      "heading_deg": 220.0,
      "speed_mps": 290.39732853679567,
      "on_ground": false
    },
    {
      "t": 1782423036,
      "t_rel": 1955.0,
      "lat": 46.7237,
      "lon": 5.8658,
      "alt_m": 10363.0,
      "heading_deg": 220.0,
      "speed_mps": 112.33664254635542,
      "on_ground": false
    },
    {
      "t": 1782423037,
      "t_rel": 1956.0,
      "lat": 46.7219,
      "lon": 5.8635,
      "alt_m": 10668.0,
      "heading_deg": 220.0,
      "speed_mps": 266.0798016249881,
      "on_ground": false
    },
    {
      "t": 1782423039,
      "t_rel": 1958.0,
      "lat": 46.7185,
      "lon": 5.8594,
      "alt_m": 10363.0,
      "heading_deg": 220.0,
      "speed_mps": 245.26368340199767,
      "on_ground": false
    },
    {
      "t": 1782423041,
      "t_rel": 1960.0,
      "lat": 46.7153,
      "lon": 5.8555,
      "alt_m": 10668.0,
      "heading_deg": 220.0,
      "speed_mps": 231.84539946128612,
      "on_ground": false
    },
    {
      "t": 1782423043,
      "t_rel": 1962.0,
      "lat": 46.7121,
      "lon": 5.8516,
      "alt_m": 10363.0,
      "heading_deg": 220.0,
      "speed_mps": 231.85105213337408,
      "on_ground": false
    },
    {
      "t": 1782423044,
      "t_rel": 1963.0,
      "lat": 46.7105,
      "lon": 5.8495,
      "alt_m": 10668.0,
      "heading_deg": 220.0,
      "speed_mps": 239.34979131541093,
      "on_ground": false
    },
    {
      "t": 1782423125,
      "t_rel": 2044.0,
      "lat": 46.5804,
      "lon": 5.6898,
      "alt_m": 10668.0,
      "heading_deg": 221.0,
      "speed_mps": 233.557687843,
      "on_ground": false
    },
    {
      "t": 1782423137,
      "t_rel": 2056.0,
      "lat": 46.5622,
      "lon": 5.6653,
      "alt_m": 10668.0,
      "heading_deg": 223.0,
      "speed_mps": 229.77889103770323,
      "on_ground": false
    },
    {
      "t": 1782423182,
      "t_rel": 2101.0,
      "lat": 46.4962,
      "lon": 5.5659,
      "alt_m": 10363.0,
      "heading_deg": 226.0,
      "speed_mps": 234.8436609200244,
      "on_ground": false
    },
    {
      "t": 1782423184,
      "t_rel": 2103.0,
      "lat": 46.4931,
      "lon": 5.5612,
      "alt_m": 10668.0,
      "heading_deg": 226.0,
      "speed_mps": 249.13005060976255,
      "on_ground": false
    },
    {
      "t": 1782423185,
      "t_rel": 2104.0,
      "lat": 46.4918,
      "lon": 5.5592,
      "alt_m": 10363.0,
      "heading_deg": 226.0,
      "speed_mps": 210.56263264853763,
      "on_ground": false
    },
    {
      "t": 1782423186,
      "t_rel": 2105.0,
      "lat": 46.4904,
      "lon": 5.557,
      "alt_m": 10668.0,
      "heading_deg": 226.0,
      "speed_mps": 229.34469906898465,
      "on_ground": false
    },
    {
      "t": 1782423187,
      "t_rel": 2106.0,
      "lat": 46.4887,
      "lon": 5.5546,
      "alt_m": 10363.0,
      "heading_deg": 226.0,
      "speed_mps": 263.612229863323,
      "on_ground": false
    },
    {
      "t": 1782423194,
      "t_rel": 2113.0,
      "lat": 46.4785,
      "lon": 5.539,
      "alt_m": 10668.0,
      "heading_deg": 226.0,
      "speed_mps": 235.30239463705828,
      "on_ground": false
    },
    {
      "t": 1782423255,
      "t_rel": 2174.0,
      "lat": 46.3884,
      "lon": 5.4029,
      "alt_m": 10363.0,
      "heading_deg": 226.0,
      "speed_mps": 237.08758538883887,
      "on_ground": false
    },
    {
      "t": 1782423257,
      "t_rel": 2176.0,
      "lat": 46.3854,
      "lon": 5.3985,
      "alt_m": 10668.0,
      "heading_deg": 226.0,
      "speed_mps": 237.26216929451562,
      "on_ground": false
    },
    {
      "t": 1782423531,
      "t_rel": 2450.0,
      "lat": 45.9779,
      "lon": 4.791,
      "alt_m": 10363.0,
      "heading_deg": 225.0,
      "speed_mps": 237.66390764893433,
      "on_ground": false
    },
    {
      "t": 1782423532,
      "t_rel": 2451.0,
      "lat": 45.977,
      "lon": 4.7898,
      "alt_m": 10668.0,
      "heading_deg": 225.0,
      "speed_mps": 136.43208637029582,
      "on_ground": false
    },
    {
      "t": 1782423533,
      "t_rel": 2452.0,
      "lat": 45.9755,
      "lon": 4.7876,
      "alt_m": 10363.0,
      "heading_deg": 225.0,
      "speed_mps": 238.16355078797628,
      "on_ground": false
    },
    {
      "t": 1782423534,
      "t_rel": 2453.0,
      "lat": 45.9739,
      "lon": 4.7851,
      "alt_m": 10668.0,
      "heading_deg": 225.0,
      "speed_mps": 262.6342543391817,
      "on_ground": false
    },
    {
      "t": 1782423536,
      "t_rel": 2455.0,
      "lat": 45.9709,
      "lon": 4.7807,
      "alt_m": 10363.0,
      "heading_deg": 225.0,
      "speed_mps": 238.17198775492477,
      "on_ground": false
    },
    {
      "t": 1782423537,
      "t_rel": 2456.0,
      "lat": 45.9694,
      "lon": 4.7786,
      "alt_m": 10668.0,
      "heading_deg": 225.0,
      "speed_mps": 232.7228469392435,
      "on_ground": false
    },
    {
      "t": 1782423538,
      "t_rel": 2457.0,
      "lat": 45.9681,
      "lon": 4.7766,
      "alt_m": 10363.0,
      "heading_deg": 225.0,
      "speed_mps": 211.6323522472222,
      "on_ground": false
    },
    {
      "t": 1782423622,
      "t_rel": 2541.0,
      "lat": 45.842,
      "lon": 4.5915,
      "alt_m": 10668.0,
      "heading_deg": 225.0,
      "speed_mps": 238.60945485401382,
      "on_ground": false
    },
    {
      "t": 1782423623,
      "t_rel": 2542.0,
      "lat": 45.8405,
      "lon": 4.5893,
      "alt_m": 10363.0,
      "heading_deg": 225.0,
      "speed_mps": 238.4592381058613,
      "on_ground": false
    },
    {
      "t": 1782423624,
      "t_rel": 2543.0,
      "lat": 45.839,
      "lon": 4.5871,
      "alt_m": 10668.0,
      "heading_deg": 225.0,
      "speed_mps": 238.46252170283984,
      "on_ground": false
    },
    {
      "t": 1782423625,
      "t_rel": 2544.0,
      "lat": 45.8371,
      "lon": 4.5845,
      "alt_m": 10363.0,
      "heading_deg": 225.0,
      "speed_mps": 291.89753472619304,
      "on_ground": false
    },
    {
      "t": 1782423627,
      "t_rel": 2546.0,
      "lat": 45.834,
      "lon": 4.5799,
      "alt_m": 10668.0,
      "heading_deg": 225.0,
      "speed_mps": 247.90151023152742,
      "on_ground": false
    },
    {
      "t": 1782423629,
      "t_rel": 2548.0,
      "lat": 45.8311,
      "lon": 4.5757,
      "alt_m": 10363.0,
      "heading_deg": 225.0,
      "speed_mps": 229.05691912930132,
      "on_ground": false
    },
    {
      "t": 1782423630,
      "t_rel": 2549.0,
      "lat": 45.8298,
      "lon": 4.5737,
      "alt_m": 10668.0,
      "heading_deg": 225.0,
      "speed_mps": 211.91406978562748,
      "on_ground": false
    },
    {
      "t": 1782423650,
      "t_rel": 2569.0,
      "lat": 45.8001,
      "lon": 4.529,
      "alt_m": 10668.0,
      "heading_deg": 227.0,
      "speed_mps": 239.30938287008206,
      "on_ground": false
    },
    {
      "t": 1782423662,
      "t_rel": 2581.0,
      "lat": 45.7831,
      "lon": 4.5006,
      "alt_m": 10668.0,
      "heading_deg": 230.0,
      "speed_mps": 241.83617479724023,
      "on_ground": false
    },
    {
      "t": 1782423915,
      "t_rel": 2834.0,
      "lat": 45.453,
      "lon": 3.8771,
      "alt_m": 10363.0,
      "heading_deg": 232.0,
      "speed_mps": 240.38421490999232,
      "on_ground": false
    },
    {
      "t": 1782423916,
      "t_rel": 2835.0,
      "lat": 45.4516,
      "lon": 3.8743,
      "alt_m": 10668.0,
      "heading_deg": 232.0,
      "speed_mps": 268.2106601290422,
      "on_ground": false
    },
    {
      "t": 1782423923,
      "t_rel": 2842.0,
      "lat": 45.4431,
      "lon": 3.8583,
      "alt_m": 10363.0,
      "heading_deg": 232.0,
      "speed_mps": 223.66341701044243,
      "on_ground": false
    },
    {
      "t": 1782423924,
      "t_rel": 2843.0,
      "lat": 45.4417,
      "lon": 3.8557,
      "alt_m": 10668.0,
      "heading_deg": 232.0,
      "speed_mps": 255.69528672300837,
      "on_ground": false
    },
    {
      "t": 1782423930,
      "t_rel": 2849.0,
      "lat": 45.4336,
      "lon": 3.8407,
      "alt_m": 10363.0,
      "heading_deg": 232.0,
      "speed_mps": 246.13447534821196,
      "on_ground": false
    },
    {
      "t": 1782423931,
      "t_rel": 2850.0,
      "lat": 45.4323,
      "lon": 3.8382,
      "alt_m": 10668.0,
      "heading_deg": 232.0,
      "speed_mps": 242.7967202128282,
      "on_ground": false
    },
    {
      "t": 1782423943,
      "t_rel": 2862.0,
      "lat": 45.4163,
      "lon": 3.8083,
      "alt_m": 10363.0,
      "heading_deg": 232.0,
      "speed_mps": 244.52785344634503,
      "on_ground": false
    },
    {
      "t": 1782423944,
      "t_rel": 2863.0,
      "lat": 45.415,
      "lon": 3.8058,
      "alt_m": 10668.0,
      "heading_deg": 232.0,
      "speed_mps": 242.8447609890894,
      "on_ground": false
    },
    {
      "t": 1782423953,
      "t_rel": 2872.0,
      "lat": 45.4035,
      "lon": 3.7845,
      "alt_m": 10363.0,
      "heading_deg": 232.0,
      "speed_mps": 233.06587977277752,
      "on_ground": false
    },
    {
      "t": 1782423954,
      "t_rel": 2873.0,
      "lat": 45.4021,
      "lon": 3.7817,
      "alt_m": 10668.0,
      "heading_deg": 232.0,
      "speed_mps": 268.366718760039,
      "on_ground": false
    },
    {
      "t": 1782423957,
      "t_rel": 2876.0,
      "lat": 45.3983,
      "lon": 3.7746,
      "alt_m": 10363.0,
      "heading_deg": 232.0,
      "speed_mps": 232.33829579078926,
      "on_ground": false
    },
    {
      "t": 1782423980,
      "t_rel": 2899.0,
      "lat": 45.3674,
      "lon": 3.717,
      "alt_m": 10668.0,
      "heading_deg": 232.0,
      "speed_mps": 246.1129793542119,
      "on_ground": false
    },
    {
      "t": 1782423981,
      "t_rel": 2900.0,
      "lat": 45.3662,
      "lon": 3.7149,
      "alt_m": 10363.0,
      "heading_deg": 232.0,
      "speed_mps": 211.468327528138,
      "on_ground": false
    },
    {
      "t": 1782423983,
      "t_rel": 2902.0,
      "lat": 45.3636,
      "lon": 3.7099,
      "alt_m": 10668.0,
      "heading_deg": 232.0,
      "speed_mps": 242.9856373576008,
      "on_ground": false
    },
    {
      "t": 1782423984,
      "t_rel": 2903.0,
      "lat": 45.3624,
      "lon": 3.7077,
      "alt_m": 10363.0,
      "heading_deg": 232.0,
      "speed_mps": 217.59391906199892,
      "on_ground": false
    },
    {
      "t": 1782423985,
      "t_rel": 2904.0,
      "lat": 45.3612,
      "lon": 3.7055,
      "alt_m": 10668.0,
      "heading_deg": 232.0,
      "speed_mps": 217.59679884404454,
      "on_ground": false
    },
    {
      "t": 1782424213,
      "t_rel": 3132.0,
      "lat": 45.0585,
      "lon": 3.1471,
      "alt_m": 10363.0,
      "heading_deg": 232.0,
      "speed_mps": 242.08078745320438,
      "on_ground": false
    },
    {
      "t": 1782424214,
      "t_rel": 3133.0,
      "lat": 45.0571,
      "lon": 3.1444,
      "alt_m": 10668.0,
      "heading_deg": 232.0,
      "speed_mps": 263.0799082714902,
      "on_ground": false
    },
    {
      "t": 1782424528,
      "t_rel": 3447.0,
      "lat": 44.6451,
      "lon": 2.3958,
      "alt_m": 10363.0,
      "heading_deg": 231.0,
      "speed_mps": 237.92138114354768,
      "on_ground": false
    },
    {
      "t": 1782424529,
      "t_rel": 3448.0,
      "lat": 44.6436,
      "lon": 2.3933,
      "alt_m": 10668.0,
      "heading_deg": 231.0,
      "speed_mps": 258.7234846218755,
      "on_ground": false
    },
    {
      "t": 1782424531,
      "t_rel": 3450.0,
      "lat": 44.6412,
      "lon": 2.3889,
      "alt_m": 10363.0,
      "heading_deg": 231.0,
      "speed_mps": 219.3165135592084,
      "on_ground": false
    },
    {
      "t": 1782424532,
      "t_rel": 3451.0,
      "lat": 44.6401,
      "lon": 2.3869,
      "alt_m": 10668.0,
      "heading_deg": 231.0,
      "speed_mps": 199.99905106620673,
      "on_ground": false
    },
    {
      "t": 1782424533,
      "t_rel": 3452.0,
      "lat": 44.6391,
      "lon": 2.3853,
      "alt_m": 10363.0,
      "heading_deg": 231.0,
      "speed_mps": 168.49250967119934,
      "on_ground": false
    },
    {
      "t": 1782424534,
      "t_rel": 3453.0,
      "lat": 44.6377,
      "lon": 2.3828,
      "alt_m": 10668.0,
      "heading_deg": 231.0,
      "speed_mps": 251.71455154003365,
      "on_ground": false
    },
    {
      "t": 1782424538,
      "t_rel": 3457.0,
      "lat": 44.6326,
      "lon": 2.3736,
      "alt_m": 10363.0,
      "heading_deg": 231.0,
      "speed_mps": 230.69423390535138,
      "on_ground": false
    },
    {
      "t": 1782424539,
      "t_rel": 3458.0,
      "lat": 44.6313,
      "lon": 2.3713,
      "alt_m": 10668.0,
      "heading_deg": 231.0,
      "speed_mps": 232.42081439782555,
      "on_ground": false
    },
    {
      "t": 1782424543,
      "t_rel": 3462.0,
      "lat": 44.6261,
      "lon": 2.3619,
      "alt_m": 10363.0,
      "heading_deg": 231.0,
      "speed_mps": 235.54007004687574,
      "on_ground": false
    },
    {
      "t": 1782424545,
      "t_rel": 3464.0,
      "lat": 44.6231,
      "lon": 2.3567,
      "alt_m": 10668.0,
      "heading_deg": 231.0,
      "speed_mps": 264.87485824367457,
      "on_ground": false
    },
    {
      "t": 1782424546,
      "t_rel": 3465.0,
      "lat": 44.6218,
      "lon": 2.3544,
      "alt_m": 10363.0,
      "heading_deg": 231.0,
      "speed_mps": 232.44414161948438,
      "on_ground": false
    },
    {
      "t": 1782424548,
      "t_rel": 3467.0,
      "lat": 44.6192,
      "lon": 2.3498,
      "alt_m": 10668.0,
      "heading_deg": 231.0,
      "speed_mps": 232.448929486323,
      "on_ground": false
    },
    {
      "t": 1782424552,
      "t_rel": 3471.0,
      "lat": 44.6145,
      "lon": 2.3414,
      "alt_m": 10363.0,
      "heading_deg": 231.0,
      "speed_mps": 211.41997584219465,
      "on_ground": false
    },
    {
      "t": 1782424554,
      "t_rel": 3473.0,
      "lat": 44.6118,
      "lon": 2.3366,
      "alt_m": 10668.0,
      "heading_deg": 231.0,
      "speed_mps": 242.12396462955792,
      "on_ground": false
    },
    {
      "t": 1782424555,
      "t_rel": 3474.0,
      "lat": 44.6105,
      "lon": 2.3344,
      "alt_m": 10363.0,
      "heading_deg": 231.0,
      "speed_mps": 226.32597670997635,
      "on_ground": false
    },
    {
      "t": 1782424557,
      "t_rel": 3476.0,
      "lat": 44.6082,
      "lon": 2.3303,
      "alt_m": 10668.0,
      "heading_deg": 231.0,
      "speed_mps": 206.60730419376426,
      "on_ground": false
    },
    {
      "t": 1782424558,
      "t_rel": 3477.0,
      "lat": 44.6064,
      "lon": 2.3271,
      "alt_m": 10363.0,
      "heading_deg": 231.0,
      "speed_mps": 322.8519719220429,
      "on_ground": false
    },
    {
      "t": 1782424561,
      "t_rel": 3480.0,
      "lat": 44.6029,
      "lon": 2.3209,
      "alt_m": 10668.0,
      "heading_deg": 231.0,
      "speed_mps": 208.8019586169037,
      "on_ground": false
    },
    {
      "t": 1782424563,
      "t_rel": 3482.0,
      "lat": 44.6002,
      "lon": 2.3162,
      "alt_m": 10363.0,
      "heading_deg": 231.0,
      "speed_mps": 239.06013663791555,
      "on_ground": false
    },
    {
      "t": 1782424566,
      "t_rel": 3485.0,
      "lat": 44.5965,
      "lon": 2.3096,
      "alt_m": 10668.0,
      "heading_deg": 231.0,
      "speed_mps": 221.69488189407943,
      "on_ground": false
    },
    {
      "t": 1782424567,
      "t_rel": 3486.0,
      "lat": 44.5951,
      "lon": 2.3071,
      "alt_m": 10363.0,
      "heading_deg": 231.0,
      "speed_mps": 251.82864516109257,
      "on_ground": false
    },
    {
      "t": 1782424590,
      "t_rel": 3509.0,
      "lat": 44.5654,
      "lon": 2.2547,
      "alt_m": 10363.0,
      "heading_deg": 231.0,
      "speed_mps": 230.59819958685966,
      "on_ground": false
    },
    {
      "t": 1782424662,
      "t_rel": 3581.0,
      "lat": 44.4679,
      "lon": 2.0979,
      "alt_m": 10668.0,
      "heading_deg": 228.0,
      "speed_mps": 229.10284552026113,
      "on_ground": false
    },
    {
      "t": 1782424663,
      "t_rel": 3582.0,
      "lat": 44.4666,
      "lon": 2.0957,
      "alt_m": 10363.0,
      "heading_deg": 228.0,
      "speed_mps": 226.6577292429963,
      "on_ground": false
    },
    {
      "t": 1782424738,
      "t_rel": 3657.0,
      "lat": 44.3635,
      "lon": 1.9317,
      "alt_m": 10668.0,
      "heading_deg": 228.0,
      "speed_mps": 231.36223230864582,
      "on_ground": false
    },
    {
      "t": 1782424739,
      "t_rel": 3658.0,
      "lat": 44.3621,
      "lon": 1.9295,
      "alt_m": 10363.0,
      "heading_deg": 228.0,
      "speed_mps": 234.1391928902758,
      "on_ground": false
    },
    {
      "t": 1782424749,
      "t_rel": 3668.0,
      "lat": 44.3483,
      "lon": 1.9076,
      "alt_m": 10668.0,
      "heading_deg": 228.0,
      "speed_mps": 232.08648483436258,
      "on_ground": false
    },
    {
      "t": 1782424919,
      "t_rel": 3838.0,
      "lat": 44.1121,
      "lon": 1.5359,
      "alt_m": 10363.0,
      "heading_deg": 228.0,
      "speed_mps": 232.84645837827838,
      "on_ground": false
    },
    {
      "t": 1782424920,
      "t_rel": 3839.0,
      "lat": 44.1106,
      "lon": 1.5336,
      "alt_m": 10668.0,
      "heading_deg": 228.0,
      "speed_mps": 248.06773337129133,
      "on_ground": false
    },
    {
      "t": 1782424924,
      "t_rel": 3843.0,
      "lat": 44.1048,
      "lon": 1.5246,
      "alt_m": 10363.0,
      "heading_deg": 228.0,
      "speed_mps": 241.38721792220855,
      "on_ground": false
    },
    {
      "t": 1782424925,
      "t_rel": 3844.0,
      "lat": 44.1036,
      "lon": 1.5226,
      "alt_m": 10668.0,
      "heading_deg": 227.0,
      "speed_mps": 208.10178636988473,
      "on_ground": false
    },
    {
      "t": 1782424927,
      "t_rel": 3846.0,
      "lat": 44.1003,
      "lon": 1.5177,
      "alt_m": 10363.0,
      "heading_deg": 227.0,
      "speed_mps": 268.20385377020744,
      "on_ground": false
    },
    {
      "t": 1782424934,
      "t_rel": 3853.0,
      "lat": 44.0906,
      "lon": 1.5039,
      "alt_m": 10363.0,
      "heading_deg": 225.0,
      "speed_mps": 220.2899552255419,
      "on_ground": false
    },
    {
      "t": 1782424941,
      "t_rel": 3860.0,
      "lat": 44.0798,
      "lon": 1.4895,
      "alt_m": 10363.0,
      "heading_deg": 223.0,
      "speed_mps": 237.54842798491745,
      "on_ground": false
    },
    {
      "t": 1782425041,
      "t_rel": 3960.0,
      "lat": 43.9189,
      "lon": 1.2987,
      "alt_m": 10668.0,
      "heading_deg": 220.0,
      "speed_mps": 235.16278288677105,
      "on_ground": false
    },
    {
      "t": 1782425042,
      "t_rel": 3961.0,
      "lat": 43.9171,
      "lon": 1.2966,
      "alt_m": 10363.0,
      "heading_deg": 220.0,
      "speed_mps": 261.444331120634,
      "on_ground": false
    },
    {
      "t": 1782425051,
      "t_rel": 3970.0,
      "lat": 43.9033,
      "lon": 1.2803,
      "alt_m": 10668.0,
      "heading_deg": 220.0,
      "speed_mps": 223.87346177228252,
      "on_ground": false
    },
    {
      "t": 1782425054,
      "t_rel": 3973.0,
      "lat": 43.8982,
      "lon": 1.2742,
      "alt_m": 10363.0,
      "heading_deg": 220.0,
      "speed_mps": 249.54589956994508,
      "on_ground": false
    },
    {
      "t": 1782425058,
      "t_rel": 3977.0,
      "lat": 43.8918,
      "lon": 1.2667,
      "alt_m": 10668.0,
      "heading_deg": 220.0,
      "speed_mps": 232.86239746622746,
      "on_ground": false
    },
    {
      "t": 1782425059,
      "t_rel": 3978.0,
      "lat": 43.8902,
      "lon": 1.2648,
      "alt_m": 10363.0,
      "heading_deg": 220.0,
      "speed_mps": 234.1665001250182,
      "on_ground": false
    },
    {
      "t": 1782425060,
      "t_rel": 3979.0,
      "lat": 43.8888,
      "lon": 1.263,
      "alt_m": 10668.0,
      "heading_deg": 220.0,
      "speed_mps": 212.22744125621585,
      "on_ground": false
    },
    {
      "t": 1782425063,
      "t_rel": 3982.0,
      "lat": 43.8843,
      "lon": 1.2577,
      "alt_m": 10363.0,
      "heading_deg": 220.0,
      "speed_mps": 218.77991023561924,
      "on_ground": false
    },
    {
      "t": 1782425064,
      "t_rel": 3983.0,
      "lat": 43.8826,
      "lon": 1.2556,
      "alt_m": 10668.0,
      "heading_deg": 220.0,
      "speed_mps": 253.09777781349626,
      "on_ground": false
    },
    {
      "t": 1782425065,
      "t_rel": 3984.0,
      "lat": 43.8811,
      "lon": 1.254,
      "alt_m": 10363.0,
      "heading_deg": 220.0,
      "speed_mps": 210.38910944224375,
      "on_ground": false
    },
    {
      "t": 1782425066,
      "t_rel": 3985.0,
      "lat": 43.8795,
      "lon": 1.2521,
      "alt_m": 10668.0,
      "heading_deg": 220.0,
      "speed_mps": 234.1842844914015,
      "on_ground": false
    },
    {
      "t": 1782425067,
      "t_rel": 3986.0,
      "lat": 43.8771,
      "lon": 1.2492,
      "alt_m": 10363.0,
      "heading_deg": 220.0,
      "speed_mps": 353.9005161837405,
      "on_ground": false
    },
    {
      "t": 1782425069,
      "t_rel": 3988.0,
      "lat": 43.8742,
      "lon": 1.2458,
      "alt_m": 10668.0,
      "heading_deg": 220.0,
      "speed_mps": 211.10050563999272,
      "on_ground": false
    },
    {
      "t": 1782425070,
      "t_rel": 3989.0,
      "lat": 43.8726,
      "lon": 1.2439,
      "alt_m": 10363.0,
      "heading_deg": 220.0,
      "speed_mps": 234.1957520607461,
      "on_ground": false
    },
    {
      "t": 1782425108,
      "t_rel": 4027.0,
      "lat": 43.8118,
      "lon": 1.1714,
      "alt_m": 10668.0,
      "heading_deg": 220.0,
      "speed_mps": 234.6599369216984,
      "on_ground": false
    },
    {
      "t": 1782425109,
      "t_rel": 4028.0,
      "lat": 43.8109,
      "lon": 1.1704,
      "alt_m": 10363.0,
      "heading_deg": 220.0,
      "speed_mps": 128.27191033465613,
      "on_ground": false
    },
    {
      "t": 1782425111,
      "t_rel": 4030.0,
      "lat": 43.8075,
      "lon": 1.1663,
      "alt_m": 10668.0,
      "heading_deg": 220.0,
      "speed_mps": 250.58528588258838,
      "on_ground": false
    },
    {
      "t": 1782425113,
      "t_rel": 4032.0,
      "lat": 43.8043,
      "lon": 1.1626,
      "alt_m": 10363.0,
      "heading_deg": 220.0,
      "speed_mps": 231.71692998960864,
      "on_ground": false
    },
    {
      "t": 1782425116,
      "t_rel": 4035.0,
      "lat": 43.7994,
      "lon": 1.1567,
      "alt_m": 10668.0,
      "heading_deg": 220.0,
      "speed_mps": 240.61628284038702,
      "on_ground": false
    },
    {
      "t": 1782425118,
      "t_rel": 4037.0,
      "lat": 43.7963,
      "lon": 1.1531,
      "alt_m": 10363.0,
      "heading_deg": 220.0,
      "speed_mps": 224.89046857205847,
      "on_ground": false
    },
    {
      "t": 1782425121,
      "t_rel": 4040.0,
      "lat": 43.7912,
      "lon": 1.147,
      "alt_m": 10668.0,
      "heading_deg": 220.0,
      "speed_mps": 249.7369507230743,
      "on_ground": false
    },
    {
      "t": 1782425130,
      "t_rel": 4049.0,
      "lat": 43.7772,
      "lon": 1.1303,
      "alt_m": 10363.0,
      "heading_deg": 220.0,
      "speed_mps": 228.27036474024004,
      "on_ground": false
    },
    {
      "t": 1782425131,
      "t_rel": 4050.0,
      "lat": 43.7753,
      "lon": 1.1281,
      "alt_m": 10668.0,
      "heading_deg": 220.0,
      "speed_mps": 275.38077526971324,
      "on_ground": false
    },
    {
      "t": 1782425133,
      "t_rel": 4052.0,
      "lat": 43.7721,
      "lon": 1.1242,
      "alt_m": 10363.0,
      "heading_deg": 220.0,
      "speed_mps": 236.99418852517007,
      "on_ground": false
    },
    {
      "t": 1782425162,
      "t_rel": 4081.0,
      "lat": 43.7257,
      "lon": 1.0691,
      "alt_m": 10668.0,
      "heading_deg": 220.0,
      "speed_mps": 234.402539212953,
      "on_ground": false
    },
    {
      "t": 1782425164,
      "t_rel": 4083.0,
      "lat": 43.7227,
      "lon": 1.0657,
      "alt_m": 10363.0,
      "heading_deg": 220.0,
      "speed_mps": 215.5957541299822,
      "on_ground": false
    },
    {
      "t": 1782425168,
      "t_rel": 4087.0,
      "lat": 43.7162,
      "lon": 1.058,
      "alt_m": 10668.0,
      "heading_deg": 219.0,
      "speed_mps": 237.86957239140665,
      "on_ground": false
    },
    {
      "t": 1782425169,
      "t_rel": 4088.0,
      "lat": 43.7145,
      "lon": 1.0562,
      "alt_m": 10363.0,
      "heading_deg": 219.0,
      "speed_mps": 238.0356134669825,
      "on_ground": false
    },
    {
      "t": 1782425173,
      "t_rel": 4092.0,
      "lat": 43.7086,
      "lon": 1.0496,
      "alt_m": 10668.0,
      "heading_deg": 219.0,
      "speed_mps": 210.92118645220015,
      "on_ground": false
    },
    {
      "t": 1782425175,
      "t_rel": 4094.0,
      "lat": 43.706,
      "lon": 1.0466,
      "alt_m": 10363.0,
      "heading_deg": 219.0,
      "speed_mps": 188.23652407258794,
      "on_ground": false
    },
    {
      "t": 1782425175,
      "t_rel": 4094.0,
      "lat": 43.7045,
      "lon": 1.045,
      "alt_m": 10668.0,
      "heading_deg": 219.0,
      "speed_mps": 188.23652407258794,
      "on_ground": false
    },
    {
      "t": 1782425176,
      "t_rel": 4095.0,
      "lat": 43.7032,
      "lon": 1.0435,
      "alt_m": 10363.0,
      "heading_deg": 219.0,
      "speed_mps": 188.24096904003824,
      "on_ground": false
    },
    {
      "t": 1782425177,
      "t_rel": 4096.0,
      "lat": 43.7013,
      "lon": 1.0413,
      "alt_m": 10668.0,
      "heading_deg": 219.0,
      "speed_mps": 275.5209370020638,
      "on_ground": false
    },
    {
      "t": 1782425178,
      "t_rel": 4097.0,
      "lat": 43.6996,
      "lon": 1.0395,
      "alt_m": 10363.0,
      "heading_deg": 218.0,
      "speed_mps": 238.05747319929995,
      "on_ground": false
    },
    {
      "t": 1782425179,
      "t_rel": 4098.0,
      "lat": 43.6982,
      "lon": 1.0379,
      "alt_m": 10668.0,
      "heading_deg": 218.0,
      "speed_mps": 201.93787689026894,
      "on_ground": false
    },
    {
      "t": 1782425325,
      "t_rel": 4244.0,
      "lat": 43.4592,
      "lon": 0.7766,
      "alt_m": 10363.0,
      "heading_deg": 218.0,
      "speed_mps": 232.20042067075642,
      "on_ground": false
    },
    {
      "t": 1782425330,
      "t_rel": 4249.0,
      "lat": 43.4512,
      "lon": 0.7679,
      "alt_m": 10668.0,
      "heading_deg": 218.0,
      "speed_mps": 226.6683452390452,
      "on_ground": false
    },
    {
      "t": 1782425331,
      "t_rel": 4250.0,
      "lat": 43.4496,
      "lon": 0.7661,
      "alt_m": 10363.0,
      "heading_deg": 218.0,
      "speed_mps": 229.70797180433746,
      "on_ground": false
    },
    {
      "t": 1782425393,
      "t_rel": 4312.0,
      "lat": 43.3487,
      "lon": 0.654,
      "alt_m": 10668.0,
      "heading_deg": 219.0,
      "speed_mps": 232.56311617969493,
      "on_ground": false
    },
    {
      "t": 1782425405,
      "t_rel": 4324.0,
      "lat": 43.3296,
      "lon": 0.6325,
      "alt_m": 10363.0,
      "heading_deg": 219.0,
      "speed_mps": 228.73303364913298,
      "on_ground": false
    },
    {
      "t": 1782425406,
      "t_rel": 4325.0,
      "lat": 43.328,
      "lon": 0.6307,
      "alt_m": 10668.0,
      "heading_deg": 219.0,
      "speed_mps": 229.89266819415352,
      "on_ground": false
    },
    {
      "t": 1782425407,
      "t_rel": 4326.0,
      "lat": 43.3264,
      "lon": 0.6289,
      "alt_m": 10363.0,
      "heading_deg": 219.0,
      "speed_mps": 229.89509712365034,
      "on_ground": false
    },
    {
      "t": 1782425408,
      "t_rel": 4327.0,
      "lat": 43.3248,
      "lon": 0.6271,
      "alt_m": 10668.0,
      "heading_deg": 219.0,
      "speed_mps": 229.89752601832615,
      "on_ground": false
    },
    {
      "t": 1782425413,
      "t_rel": 4332.0,
      "lat": 43.3164,
      "lon": 0.6177,
      "alt_m": 10363.0,
      "heading_deg": 219.0,
      "speed_mps": 240.88880637501592,
      "on_ground": false
    },
    {
      "t": 1782425414,
      "t_rel": 4333.0,
      "lat": 43.3155,
      "lon": 0.6166,
      "alt_m": 10668.0,
      "heading_deg": 219.0,
      "speed_mps": 133.92154213133438,
      "on_ground": false
    },
    {
      "t": 1782425463,
      "t_rel": 4382.0,
      "lat": 43.2363,
      "lon": 0.5287,
      "alt_m": 10363.0,
      "heading_deg": 218.0,
      "speed_mps": 231.06839903563292,
      "on_ground": false
    },
    {
      "t": 1782425464,
      "t_rel": 4383.0,
      "lat": 43.2346,
      "lon": 0.5268,
      "alt_m": 10668.0,
      "heading_deg": 218.0,
      "speed_mps": 243.7708204056184,
      "on_ground": false
    },
    {
      "t": 1782425480,
      "t_rel": 4399.0,
      "lat": 43.2096,
      "lon": 0.4992,
      "alt_m": 10363.0,
      "heading_deg": 218.0,
      "speed_mps": 222.98654899135474,
      "on_ground": false
    },
    {
      "t": 1782425557,
      "t_rel": 4476.0,
      "lat": 43.0888,
      "lon": 0.3644,
      "alt_m": 10668.0,
      "heading_deg": 219.0,
      "speed_mps": 224.94781500319823,
      "on_ground": false
    },
    {
      "t": 1782425585,
      "t_rel": 4504.0,
      "lat": 43.0453,
      "lon": 0.3161,
      "alt_m": 10363.0,
      "heading_deg": 218.0,
      "speed_mps": 222.43729825743708,
      "on_ground": false
    },
    {
      "t": 1782425586,
      "t_rel": 4505.0,
      "lat": 43.0437,
      "lon": 0.3144,
      "alt_m": 10668.0,
      "heading_deg": 217.0,
      "speed_mps": 225.25026304183186,
      "on_ground": false
    },
    {
      "t": 1782425759,
      "t_rel": 4678.0,
      "lat": 42.7544,
      "lon": 0.027,
      "alt_m": 10363.0,
      "heading_deg": 215.0,
      "speed_mps": 229.97308559818393,
      "on_ground": false
    },
    {
      "t": 1782425760,
      "t_rel": 4679.0,
      "lat": 42.753,
      "lon": 0.0255,
      "alt_m": 10668.0,
      "heading_deg": 215.0,
      "speed_mps": 198.0743924476863,
      "on_ground": false
    },
    {
      "t": 1782425761,
      "t_rel": 4680.0,
      "lat": 42.7513,
      "lon": 0.0239,
      "alt_m": 10363.0,
      "heading_deg": 215.0,
      "speed_mps": 229.78188443535754,
      "on_ground": false
    },
    {
      "t": 1782425839,
      "t_rel": 4758.0,
      "lat": 42.6243,
      "lon": -0.101,
      "alt_m": 10668.0,
      "heading_deg": 215.0,
      "speed_mps": 223.40123933224015,
      "on_ground": false
    },
    {
      "t": 1782426283,
      "t_rel": 5202.0,
      "lat": 41.8882,
      "lon": -0.8126,
      "alt_m": 10363.0,
      "heading_deg": 215.0,
      "speed_mps": 226.67534141530274,
      "on_ground": false
    },
    {
      "t": 1782426285,
      "t_rel": 5204.0,
      "lat": 41.8847,
      "lon": -0.8159,
      "alt_m": 10668.0,
      "heading_deg": 215.0,
      "speed_mps": 237.74411947865946,
      "on_ground": false
    },
    {
      "t": 1782426286,
      "t_rel": 5205.0,
      "lat": 41.883,
      "lon": -0.8175,
      "alt_m": 10363.0,
      "heading_deg": 215.0,
      "speed_mps": 230.81872016739473,
      "on_ground": false
    },
    {
      "t": 1782426365,
      "t_rel": 5284.0,
      "lat": 41.7522,
      "lon": -0.9419,
      "alt_m": 10668.0,
      "heading_deg": 215.0,
      "speed_mps": 225.6623046054821,
      "on_ground": false
    },
    {
      "t": 1782426366,
      "t_rel": 5285.0,
      "lat": 41.7505,
      "lon": -0.9435,
      "alt_m": 10363.0,
      "heading_deg": 215.0,
      "speed_mps": 230.97625202228295,
      "on_ground": false
    },
    {
      "t": 1782426368,
      "t_rel": 5287.0,
      "lat": 41.7474,
      "lon": -0.9464,
      "alt_m": 10668.0,
      "heading_deg": 215.0,
      "speed_mps": 210.17880081136823,
      "on_ground": false
    },
    {
      "t": 1782426417,
      "t_rel": 5336.0,
      "lat": 41.6664,
      "lon": -1.0238,
      "alt_m": 10668.0,
      "heading_deg": 217.0,
      "speed_mps": 225.79026337967238,
      "on_ground": false
    },
    {
      "t": 1782426428,
      "t_rel": 5347.0,
      "lat": 41.6489,
      "lon": -1.0426,
      "alt_m": 10668.0,
      "heading_deg": 219.0,
      "speed_mps": 226.83485239082736,
      "on_ground": false
    },
    {
      "t": 1782426455,
      "t_rel": 5374.0,
      "lat": 41.6084,
      "lon": -1.091,
      "alt_m": 10363.0,
      "heading_deg": 222.0,
      "speed_mps": 223.64661761815282,
      "on_ground": false
    },
    {
      "t": 1782426524,
      "t_rel": 5443.0,
      "lat": 41.5061,
      "lon": -1.2142,
      "alt_m": 10058.0,
      "heading_deg": 222.0,
      "speed_mps": 221.92358331755534,
      "on_ground": false
    },
    {
      "t": 1782426589,
      "t_rel": 5508.0,
      "lat": 41.4112,
      "lon": -1.3281,
      "alt_m": 9753.0,
      "heading_deg": 222.0,
      "speed_mps": 218.35563189734816,
      "on_ground": false
    },
    {
      "t": 1782426650,
      "t_rel": 5569.0,
      "lat": 41.3215,
      "lon": -1.4354,
      "alt_m": 9448.0,
      "heading_deg": 221.0,
      "speed_mps": 219.73636845047824,
      "on_ground": false
    },
    {
      "t": 1782426712,
      "t_rel": 5631.0,
      "lat": 41.2281,
      "lon": -1.5466,
      "alt_m": 9144.0,
      "heading_deg": 221.0,
      "speed_mps": 224.77777632166138,
      "on_ground": false
    },
    {
      "t": 1782426750,
      "t_rel": 5669.0,
      "lat": 41.1715,
      "lon": -1.6138,
      "alt_m": 8839.0,
      "heading_deg": 221.0,
      "speed_mps": 222.08391764893358,
      "on_ground": false
    },
    {
      "t": 1782426767,
      "t_rel": 5686.0,
      "lat": 41.1452,
      "lon": -1.6448,
      "alt_m": 8229.0,
      "heading_deg": 221.0,
      "speed_mps": 229.99642611446941,
      "on_ground": false
    },
    {
      "t": 1782426783,
      "t_rel": 5702.0,
      "lat": 41.1207,
      "lon": -1.6739,
      "alt_m": 8229.0,
      "heading_deg": 221.0,
      "speed_mps": 228.45702939241565,
      "on_ground": false
    },
    {
      "t": 1782426799,
      "t_rel": 5718.0,
      "lat": 41.096,
      "lon": -1.7031,
      "alt_m": 7924.0,
      "heading_deg": 221.0,
      "speed_mps": 229.8806699513434,
      "on_ground": false
    },
    {
      "t": 1782426816,
      "t_rel": 5735.0,
      "lat": 41.0696,
      "lon": -1.7343,
      "alt_m": 7620.0,
      "heading_deg": 221.0,
      "speed_mps": 231.25726898560453,
      "on_ground": false
    },
    {
      "t": 1782426829,
      "t_rel": 5748.0,
      "lat": 41.0495,
      "lon": -1.758,
      "alt_m": 7315.0,
      "heading_deg": 221.0,
      "speed_mps": 230.04866924379257,
      "on_ground": false
    },
    {
      "t": 1782426840,
      "t_rel": 5759.0,
      "lat": 41.033,
      "lon": -1.7775,
      "alt_m": 7010.0,
      "heading_deg": 221.0,
      "speed_mps": 223.43596939501586,
      "on_ground": false
    },
    {
      "t": 1782426857,
      "t_rel": 5776.0,
      "lat": 41.0052,
      "lon": -1.8102,
      "alt_m": 6705.0,
      "heading_deg": 221.0,
      "speed_mps": 243.11838778971457,
      "on_ground": false
    },
    {
      "t": 1782426874,
      "t_rel": 5793.0,
      "lat": 40.9783,
      "lon": -1.8419,
      "alt_m": 6400.0,
      "heading_deg": 221.0,
      "speed_mps": 235.48297121435985,
      "on_ground": false
    },
    {
      "t": 1782426897,
      "t_rel": 5816.0,
      "lat": 40.9423,
      "lon": -1.8842,
      "alt_m": 6096.0,
      "heading_deg": 221.0,
      "speed_mps": 232.681749593664,
      "on_ground": false
    },
    {
      "t": 1782427040,
      "t_rel": 5959.0,
      "lat": 40.7483,
      "lon": -2.1114,
      "alt_m": 6096.0,
      "heading_deg": 223.0,
      "speed_mps": 201.53730006946392,
      "on_ground": false
    },
    {
      "t": 1782427042,
      "t_rel": 5961.0,
      "lat": 40.7464,
      "lon": -2.114,
      "alt_m": 6096.0,
      "heading_deg": 225.0,
      "speed_mps": 152.1574188800333,
      "on_ground": false
    },
    {
      "t": 1782427044,
      "t_rel": 5963.0,
      "lat": 40.7442,
      "lon": -2.1172,
      "alt_m": 6096.0,
      "heading_deg": 227.0,
      "speed_mps": 182.0136889690312,
      "on_ground": false
    },
    {
      "t": 1782427045,
      "t_rel": 5964.0,
      "lat": 40.7434,
      "lon": -2.1186,
      "alt_m": 6096.0,
      "heading_deg": 229.0,
      "speed_mps": 147.72876802489756,
      "on_ground": false
    },
    {
      "t": 1782427046,
      "t_rel": 5965.0,
      "lat": 40.7426,
      "lon": -2.12,
      "alt_m": 6096.0,
      "heading_deg": 230.0,
      "speed_mps": 147.72990064675574,
      "on_ground": false
    },
    {
      "t": 1782427048,
      "t_rel": 5967.0,
      "lat": 40.7407,
      "lon": -2.1232,
      "alt_m": 6096.0,
      "heading_deg": 232.0,
      "speed_mps": 171.25697452138766,
      "on_ground": false
    },
    {
      "t": 1782427049,
      "t_rel": 5968.0,
      "lat": 40.7399,
      "lon": -2.1248,
      "alt_m": 6096.0,
      "heading_deg": 234.0,
      "speed_mps": 161.50559456182992,
      "on_ground": false
    },
    {
      "t": 1782427051,
      "t_rel": 5970.0,
      "lat": 40.7386,
      "lon": -2.1276,
      "alt_m": 6096.0,
      "heading_deg": 236.0,
      "speed_mps": 138.3345740078189,
      "on_ground": false
    },
    {
      "t": 1782427053,
      "t_rel": 5972.0,
      "lat": 40.7373,
      "lon": -2.1303,
      "alt_m": 6096.0,
      "heading_deg": 237.0,
      "speed_mps": 134.76258102004147,
      "on_ground": false
    },
    {
      "t": 1782427054,
      "t_rel": 5973.0,
      "lat": 40.7363,
      "lon": -2.1328,
      "alt_m": 6096.0,
      "heading_deg": 240.0,
      "speed_mps": 238.1838010368031,
      "on_ground": false
    },
    {
      "t": 1782427055,
      "t_rel": 5974.0,
      "lat": 40.7356,
      "lon": -2.1347,
      "alt_m": 6096.0,
      "heading_deg": 240.0,
      "speed_mps": 178.0046878056521,
      "on_ground": false
    },
    {
      "t": 1782427056,
      "t_rel": 5975.0,
      "lat": 40.735,
      "lon": -2.1364,
      "alt_m": 6096.0,
      "heading_deg": 242.0,
      "speed_mps": 158.0109992824969,
      "on_ground": false
    },
    {
      "t": 1782427058,
      "t_rel": 5977.0,
      "lat": 40.7338,
      "lon": -2.14,
      "alt_m": 6096.0,
      "heading_deg": 244.0,
      "speed_mps": 165.68878680611672,
      "on_ground": false
    },
    {
      "t": 1782427059,
      "t_rel": 5978.0,
      "lat": 40.7333,
      "lon": -2.1418,
      "alt_m": 6096.0,
      "heading_deg": 247.0,
      "speed_mps": 161.53416827435458,
      "on_ground": false
    },
    {
      "t": 1782427060,
      "t_rel": 5979.0,
      "lat": 40.7328,
      "lon": -2.1434,
      "alt_m": 6096.0,
      "heading_deg": 248.0,
      "speed_mps": 145.82844869334977,
      "on_ground": false
    },
    {
      "t": 1782427061,
      "t_rel": 5980.0,
      "lat": 40.7322,
      "lon": -2.1458,
      "alt_m": 6096.0,
      "heading_deg": 250.0,
      "speed_mps": 212.94426492152127,
      "on_ground": false
    },
    {
      "t": 1782427062,
      "t_rel": 5981.0,
      "lat": 40.7318,
      "lon": -2.1479,
      "alt_m": 6096.0,
      "heading_deg": 251.0,
      "speed_mps": 182.4508473059727,
      "on_ground": false
    },
    {
      "t": 1782427064,
      "t_rel": 5983.0,
      "lat": 40.731,
      "lon": -2.1516,
      "alt_m": 6096.0,
      "heading_deg": 253.0,
      "speed_mps": 162.1040374275697,
      "on_ground": false
    },
    {
      "t": 1782427065,
      "t_rel": 5984.0,
      "lat": 40.7309,
      "lon": -2.1526,
      "alt_m": 6096.0,
      "heading_deg": 256.0,
      "speed_mps": 84.99203128932844,
      "on_ground": false
    },
    {
      "t": 1782427066,
      "t_rel": 5985.0,
      "lat": 40.7306,
      "lon": -2.1547,
      "alt_m": 6096.0,
      "heading_deg": 257.0,
      "speed_mps": 180.066616195435,
      "on_ground": false
    },
    {
      "t": 1782427067,
      "t_rel": 5986.0,
      "lat": 40.7304,
      "lon": -2.1566,
      "alt_m": 6096.0,
      "heading_deg": 259.0,
      "speed_mps": 161.63516735087714,
      "on_ground": false
    },
    {
      "t": 1782427069,
      "t_rel": 5988.0,
      "lat": 40.73,
      "lon": -2.1609,
      "alt_m": 6096.0,
      "heading_deg": 260.0,
      "speed_mps": 182.5241704160795,
      "on_ground": false
    },
    {
      "t": 1782427070,
      "t_rel": 5989.0,
      "lat": 40.7299,
      "lon": -2.1631,
      "alt_m": 6096.0,
      "heading_deg": 263.0,
      "speed_mps": 185.7113000465617,
      "on_ground": false
    },
    {
      "t": 1782427071,
      "t_rel": 5990.0,
      "lat": 40.7298,
      "lon": -2.1649,
      "alt_m": 6096.0,
      "heading_deg": 265.0,
      "speed_mps": 152.0802782578466,
      "on_ground": false
    },
    {
      "t": 1782427072,
      "t_rel": 5991.0,
      "lat": 40.7298,
      "lon": -2.1668,
      "alt_m": 6096.0,
      "heading_deg": 267.0,
      "speed_mps": 160.099638137398,
      "on_ground": false
    },
    {
      "t": 1782427073,
      "t_rel": 5992.0,
      "lat": 40.7298,
      "lon": -2.169,
      "alt_m": 6096.0,
      "heading_deg": 268.0,
      "speed_mps": 185.37852836840236,
      "on_ground": false
    },
    {
      "t": 1782427074,
      "t_rel": 5993.0,
      "lat": 40.7299,
      "lon": -2.1706,
      "alt_m": 6096.0,
      "heading_deg": 270.0,
      "speed_mps": 135.2784161171748,
      "on_ground": false
    },
    {
      "t": 1782427075,
      "t_rel": 5994.0,
      "lat": 40.73,
      "lon": -2.1726,
      "alt_m": 6096.0,
      "heading_deg": 271.0,
      "speed_mps": 168.8919944863037,
      "on_ground": false
    },
    {
      "t": 1782427076,
      "t_rel": 5995.0,
      "lat": 40.7301,
      "lon": -2.1745,
      "alt_m": 6096.0,
      "heading_deg": 273.0,
      "speed_mps": 160.48471781027388,
      "on_ground": false
    },
    {
      "t": 1782427077,
      "t_rel": 5996.0,
      "lat": 40.7303,
      "lon": -2.1765,
      "alt_m": 6096.0,
      "heading_deg": 274.0,
      "speed_mps": 169.9859457351474,
      "on_ground": false
    },
    {
      "t": 1782427079,
      "t_rel": 5998.0,
      "lat": 40.7307,
      "lon": -2.1807,
      "alt_m": 6096.0,
      "heading_deg": 276.0,
      "speed_mps": 178.34238407613157,
      "on_ground": false
    },
    {
      "t": 1782427088,
      "t_rel": 6007.0,
      "lat": 40.7328,
      "lon": -2.199,
      "alt_m": 5791.0,
      "heading_deg": 278.0,
      "speed_mps": 173.28308351704732,
      "on_ground": false
    },
    {
      "t": 1782427130,
      "t_rel": 6049.0,
      "lat": 40.7427,
      "lon": -2.281,
      "alt_m": 5486.0,
      "heading_deg": 278.0,
      "speed_mps": 166.56881443458377,
      "on_ground": false
    },
    {
      "t": 1782427175,
      "t_rel": 6094.0,
      "lat": 40.753,
      "lon": -2.3682,
      "alt_m": 5181.0,
      "heading_deg": 278.0,
      "speed_mps": 165.21079864653933,
      "on_ground": false
    },
    {
      "t": 1782427233,
      "t_rel": 6152.0,
      "lat": 40.7661,
      "lon": -2.4795,
      "alt_m": 4876.0,
      "heading_deg": 278.0,
      "speed_mps": 163.56503235637402,
      "on_ground": false
    },
    {
      "t": 1782427286,
      "t_rel": 6205.0,
      "lat": 40.7778,
      "lon": -2.5796,
      "alt_m": 4876.0,
      "heading_deg": 277.0,
      "speed_mps": 160.92797240660724,
      "on_ground": false
    },
    {
      "t": 1782427288,
      "t_rel": 6207.0,
      "lat": 40.778,
      "lon": -2.5824,
      "alt_m": 4876.0,
      "heading_deg": 275.0,
      "speed_mps": 118.40611078599355,
      "on_ground": false
    },
    {
      "t": 1782427290,
      "t_rel": 6209.0,
      "lat": 40.7781,
      "lon": -2.5873,
      "alt_m": 4572.0,
      "heading_deg": 272.0,
      "speed_mps": 206.36940952893283,
      "on_ground": false
    },
    {
      "t": 1782427291,
      "t_rel": 6210.0,
      "lat": 40.7781,
      "lon": -2.5894,
      "alt_m": 4572.0,
      "heading_deg": 271.0,
      "speed_mps": 176.8237275594365,
      "on_ground": false
    },
    {
      "t": 1782427292,
      "t_rel": 6211.0,
      "lat": 40.7781,
      "lon": -2.5909,
      "alt_m": 4572.0,
      "heading_deg": 270.0,
      "speed_mps": 126.30266254393706,
      "on_ground": false
    },
    {
      "t": 1782427293,
      "t_rel": 6212.0,
      "lat": 40.778,
      "lon": -2.5928,
      "alt_m": 4572.0,
      "heading_deg": 269.0,
      "speed_mps": 160.36945201723827,
      "on_ground": false
    },
    {
      "t": 1782427294,
      "t_rel": 6213.0,
      "lat": 40.7779,
      "lon": -2.5947,
      "alt_m": 4572.0,
      "heading_deg": 267.0,
      "speed_mps": 160.36969227030113,
      "on_ground": false
    },
    {
      "t": 1782427295,
      "t_rel": 6214.0,
      "lat": 40.7778,
      "lon": -2.5967,
      "alt_m": 4572.0,
      "heading_deg": 266.0,
      "speed_mps": 168.77088684820185,
      "on_ground": false
    },
    {
      "t": 1782427296,
      "t_rel": 6215.0,
      "lat": 40.7776,
      "lon": -2.5984,
      "alt_m": 4572.0,
      "heading_deg": 265.0,
      "speed_mps": 144.8611152090213,
      "on_ground": false
    },
    {
      "t": 1782427297,
      "t_rel": 6216.0,
      "lat": 40.7775,
      "lon": -2.6003,
      "alt_m": 4572.0,
      "heading_deg": 263.0,
      "speed_mps": 160.37065327792743,
      "on_ground": false
    },
    {
      "t": 1782427298,
      "t_rel": 6217.0,
      "lat": 40.7772,
      "lon": -2.6019,
      "alt_m": 4572.0,
      "heading_deg": 262.0,
      "speed_mps": 138.79280069304056,
      "on_ground": false
    },
    {
      "t": 1782427299,
      "t_rel": 6218.0,
      "lat": 40.777,
      "lon": -2.6036,
      "alt_m": 4572.0,
      "heading_deg": 261.0,
      "speed_mps": 144.86239275872046,
      "on_ground": false
    },
    {
      "t": 1782427300,
      "t_rel": 6219.0,
      "lat": 40.7767,
      "lon": -2.6052,
      "alt_m": 4572.0,
      "heading_deg": 259.0,
      "speed_mps": 138.79378498344013,
      "on_ground": false
    },
    {
      "t": 1782427301,
      "t_rel": 6220.0,
      "lat": 40.7764,
      "lon": -2.6074,
      "alt_m": 4572.0,
      "heading_deg": 258.0,
      "speed_mps": 188.2277710053539,
      "on_ground": false
    },
    {
      "t": 1782427302,
      "t_rel": 6221.0,
      "lat": 40.776,
      "lon": -2.6092,
      "alt_m": 4572.0,
      "heading_deg": 256.0,
      "speed_mps": 157.95887443774652,
      "on_ground": false
    },
    {
      "t": 1782427303,
      "t_rel": 6222.0,
      "lat": 40.7756,
      "lon": -2.611,
      "alt_m": 4572.0,
      "heading_deg": 255.0,
      "speed_mps": 157.95975010517122,
      "on_ground": false
    },
    {
      "t": 1782427304,
      "t_rel": 6223.0,
      "lat": 40.7751,
      "lon": -2.6131,
      "alt_m": 4572.0,
      "heading_deg": 253.0,
      "speed_mps": 185.36530759039772,
      "on_ground": false
    },
    {
      "t": 1782427305,
      "t_rel": 6224.0,
      "lat": 40.7746,
      "lon": -2.615,
      "alt_m": 4572.0,
      "heading_deg": 252.0,
      "speed_mps": 169.37609573169664,
      "on_ground": false
    },
    {
      "t": 1782427306,
      "t_rel": 6225.0,
      "lat": 40.7741,
      "lon": -2.6167,
      "alt_m": 4572.0,
      "heading_deg": 250.0,
      "speed_mps": 153.5685994519251,
      "on_ground": false
    },
    {
      "t": 1782427307,
      "t_rel": 6226.0,
      "lat": 40.7737,
      "lon": -2.618,
      "alt_m": 4572.0,
      "heading_deg": 249.0,
      "speed_mps": 118.16006837856818,
      "on_ground": false
    },
    {
      "t": 1782427308,
      "t_rel": 6227.0,
      "lat": 40.773,
      "lon": -2.6199,
      "alt_m": 4572.0,
      "heading_deg": 247.0,
      "speed_mps": 177.92372655373097,
      "on_ground": false
    },
    {
      "t": 1782427309,
      "t_rel": 6228.0,
      "lat": 40.7725,
      "lon": -2.6214,
      "alt_m": 4572.0,
      "heading_deg": 246.0,
      "speed_mps": 138.00728229946822,
      "on_ground": false
    },
    {
      "t": 1782427311,
      "t_rel": 6230.0,
      "lat": 40.7713,
      "lon": -2.624,
      "alt_m": 4572.0,
      "heading_deg": 244.0,
      "speed_mps": 128.20056774785283,
      "on_ground": false
    },
    {
      "t": 1782427312,
      "t_rel": 6231.0,
      "lat": 40.7704,
      "lon": -2.6263,
      "alt_m": 4572.0,
      "heading_deg": 241.0,
      "speed_mps": 218.01159575369812,
      "on_ground": false
    },
    {
      "t": 1782427313,
      "t_rel": 6232.0,
      "lat": 40.7697,
      "lon": -2.6277,
      "alt_m": 4572.0,
      "heading_deg": 239.0,
      "speed_mps": 141.27335523698895,
      "on_ground": false
    },
    {
      "t": 1782427314,
      "t_rel": 6233.0,
      "lat": 40.7689,
      "lon": -2.6293,
      "alt_m": 4572.0,
      "heading_deg": 238.0,
      "speed_mps": 161.45653227498153,
      "on_ground": false
    },
    {
      "t": 1782427315,
      "t_rel": 6234.0,
      "lat": 40.7682,
      "lon": -2.6307,
      "alt_m": 4572.0,
      "heading_deg": 236.0,
      "speed_mps": 141.2755762334046,
      "on_ground": false
    },
    {
      "t": 1782427316,
      "t_rel": 6235.0,
      "lat": 40.7673,
      "lon": -2.6321,
      "alt_m": 4572.0,
      "heading_deg": 235.0,
      "speed_mps": 154.64702672046403,
      "on_ground": false
    },
    {
      "t": 1782427317,
      "t_rel": 6236.0,
      "lat": 40.7665,
      "lon": -2.6335,
      "alt_m": 4572.0,
      "heading_deg": 233.0,
      "speed_mps": 147.6960577845776,
      "on_ground": false
    },
    {
      "t": 1782427318,
      "t_rel": 6237.0,
      "lat": 40.7656,
      "lon": -2.6349,
      "alt_m": 4572.0,
      "heading_deg": 231.0,
      "speed_mps": 154.64932614402085,
      "on_ground": false
    },
    {
      "t": 1782427319,
      "t_rel": 6238.0,
      "lat": 40.7648,
      "lon": -2.636,
      "alt_m": 4572.0,
      "heading_deg": 230.0,
      "speed_mps": 128.43409731241786,
      "on_ground": false
    },
    {
      "t": 1782427320,
      "t_rel": 6239.0,
      "lat": 40.7638,
      "lon": -2.6373,
      "alt_m": 4572.0,
      "heading_deg": 228.0,
      "speed_mps": 156.04898778762487,
      "on_ground": false
    },
    {
      "t": 1782427321,
      "t_rel": 6240.0,
      "lat": 40.7629,
      "lon": -2.6387,
      "alt_m": 4572.0,
      "heading_deg": 227.0,
      "speed_mps": 154.6529780576446,
      "on_ground": false
    },
    {
      "t": 1782427322,
      "t_rel": 6241.0,
      "lat": 40.762,
      "lon": -2.6398,
      "alt_m": 4572.0,
      "heading_deg": 225.0,
      "speed_mps": 136.3743398694112,
      "on_ground": false
    },
    {
      "t": 1782427323,
      "t_rel": 6242.0,
      "lat": 40.7606,
      "lon": -2.6415,
      "alt_m": 4572.0,
      "heading_deg": 224.0,
      "speed_mps": 211.5049356951733,
      "on_ground": false
    },
    {
      "t": 1782427324,
      "t_rel": 6243.0,
      "lat": 40.7598,
      "lon": -2.6424,
      "alt_m": 4572.0,
      "heading_deg": 222.0,
      "speed_mps": 116.87217296623905,
      "on_ground": false
    },
    {
      "t": 1782427325,
      "t_rel": 6244.0,
      "lat": 40.7587,
      "lon": -2.6435,
      "alt_m": 4572.0,
      "heading_deg": 221.0,
      "speed_mps": 153.44220963440972,
      "on_ground": false
    },
    {
      "t": 1782427327,
      "t_rel": 6246.0,
      "lat": 40.7566,
      "lon": -2.6458,
      "alt_m": 4572.0,
      "heading_deg": 219.0,
      "speed_mps": 151.7032319707166,
      "on_ground": false
    },
    {
      "t": 1782427353,
      "t_rel": 6272.0,
      "lat": 40.7284,
      "lon": -2.6737,
      "alt_m": 3962.0,
      "heading_deg": 217.0,
      "speed_mps": 150.7250174875958,
      "on_ground": false
    },
    {
      "t": 1782427400,
      "t_rel": 6319.0,
      "lat": 40.678,
      "lon": -2.7241,
      "alt_m": 3962.0,
      "heading_deg": 217.0,
      "speed_mps": 149.6298577059035,
      "on_ground": false
    },
    {
      "t": 1782427480,
      "t_rel": 6399.0,
      "lat": 40.5997,
      "lon": -2.8018,
      "alt_m": 3657.0,
      "heading_deg": 217.0,
      "speed_mps": 136.23716445611302,
      "on_ground": false
    },
    {
      "t": 1782427526,
      "t_rel": 6445.0,
      "lat": 40.5587,
      "lon": -2.842,
      "alt_m": 3352.0,
      "heading_deg": 216.0,
      "speed_mps": 123.57047866214444,
      "on_ground": false
    },
    {
      "t": 1782427538,
      "t_rel": 6457.0,
      "lat": 40.5479,
      "lon": -2.8526,
      "alt_m": 3352.0,
      "heading_deg": 216.0,
      "speed_mps": 124.83843184019076,
      "on_ground": false
    },
    {
      "t": 1782427541,
      "t_rel": 6460.0,
      "lat": 40.545,
      "lon": -2.8553,
      "alt_m": 3352.0,
      "heading_deg": 214.0,
      "speed_mps": 131.6686792309654,
      "on_ground": false
    },
    {
      "t": 1782427543,
      "t_rel": 6462.0,
      "lat": 40.5431,
      "lon": -2.8567,
      "alt_m": 3352.0,
      "heading_deg": 211.0,
      "speed_mps": 121.06744684088828,
      "on_ground": false
    },
    {
      "t": 1782427544,
      "t_rel": 6463.0,
      "lat": 40.5421,
      "lon": -2.8574,
      "alt_m": 3352.0,
      "heading_deg": 210.0,
      "speed_mps": 125.9483963781702,
      "on_ground": false
    },
    {
      "t": 1782427545,
      "t_rel": 6464.0,
      "lat": 40.5412,
      "lon": -2.8579,
      "alt_m": 3352.0,
      "heading_deg": 208.0,
      "speed_mps": 108.62866759921671,
      "on_ground": false
    },
    {
      "t": 1782427546,
      "t_rel": 6465.0,
      "lat": 40.5401,
      "lon": -2.8586,
      "alt_m": 3352.0,
      "heading_deg": 206.0,
      "speed_mps": 135.86650695622367,
      "on_ground": false
    },
    {
      "t": 1782427547,
      "t_rel": 6466.0,
      "lat": 40.539,
      "lon": -2.8593,
      "alt_m": 3352.0,
      "heading_deg": 204.0,
      "speed_mps": 135.86692982806835,
      "on_ground": false
    },
    {
      "t": 1782427548,
      "t_rel": 6467.0,
      "lat": 40.538,
      "lon": -2.8597,
      "alt_m": 3352.0,
      "heading_deg": 203.0,
      "speed_mps": 116.21910307199589,
      "on_ground": false
    },
    {
      "t": 1782427549,
      "t_rel": 6468.0,
      "lat": 40.5371,
      "lon": -2.8601,
      "alt_m": 3352.0,
      "heading_deg": 200.0,
      "speed_mps": 105.62998200171376,
      "on_ground": false
    },
    {
      "t": 1782427551,
      "t_rel": 6470.0,
      "lat": 40.535,
      "lon": -2.8608,
      "alt_m": 3352.0,
      "heading_deg": 199.0,
      "speed_mps": 120.4429177142849,
      "on_ground": false
    },
    {
      "t": 1782427552,
      "t_rel": 6471.0,
      "lat": 40.5341,
      "lon": -2.8611,
      "alt_m": 3352.0,
      "heading_deg": 195.0,
      "speed_mps": 103.23692599878078,
      "on_ground": false
    },
    {
      "t": 1782427553,
      "t_rel": 6472.0,
      "lat": 40.533,
      "lon": -2.8615,
      "alt_m": 3352.0,
      "heading_deg": 193.0,
      "speed_mps": 126.89978021814949,
      "on_ground": false
    },
    {
      "t": 1782427554,
      "t_rel": 6473.0,
      "lat": 40.5314,
      "lon": -2.8618,
      "alt_m": 3352.0,
      "heading_deg": 191.0,
      "speed_mps": 179.70935833335227,
      "on_ground": false
    },
    {
      "t": 1782427555,
      "t_rel": 6474.0,
      "lat": 40.5308,
      "lon": -2.8619,
      "alt_m": 3352.0,
      "heading_deg": 189.0,
      "speed_mps": 67.25011899273964,
      "on_ground": false
    },
    {
      "t": 1782427556,
      "t_rel": 6475.0,
      "lat": 40.5296,
      "lon": -2.8621,
      "alt_m": 3352.0,
      "heading_deg": 188.0,
      "speed_mps": 134.5002665146163,
      "on_ground": false
    },
    {
      "t": 1782427557,
      "t_rel": 6476.0,
      "lat": 40.5284,
      "lon": -2.8622,
      "alt_m": 3352.0,
      "heading_deg": 187.0,
      "speed_mps": 133.7013075096619,
      "on_ground": false
    },
    {
      "t": 1782427558,
      "t_rel": 6477.0,
      "lat": 40.5274,
      "lon": -2.8623,
      "alt_m": 3352.0,
      "heading_deg": 185.0,
      "speed_mps": 111.51567074395618,
      "on_ground": false
    },
    {
      "t": 1782427560,
      "t_rel": 6479.0,
      "lat": 40.5247,
      "lon": -2.8625,
      "alt_m": 3048.0,
      "heading_deg": 184.0,
      "speed_mps": 150.350906707764,
      "on_ground": false
    },
    {
      "t": 1782427561,
      "t_rel": 6480.0,
      "lat": 40.5237,
      "lon": -2.8626,
      "alt_m": 3048.0,
      "heading_deg": 183.0,
      "speed_mps": 111.51570610907093,
      "on_ground": false
    },
    {
      "t": 1782427609,
      "t_rel": 6528.0,
      "lat": 40.4703,
      "lon": -2.8641,
      "alt_m": 2743.0,
      "heading_deg": 181.0,
      "speed_mps": 123.7325744775951,
      "on_ground": false
    },
    {
      "t": 1782427646,
      "t_rel": 6565.0,
      "lat": 40.4297,
      "lon": -2.8654,
      "alt_m": 2743.0,
      "heading_deg": 182.0,
      "speed_mps": 122.0501073777762,
      "on_ground": false
    },
    {
      "t": 1782427648,
      "t_rel": 6567.0,
      "lat": 40.4269,
      "lon": -2.8658,
      "alt_m": 2743.0,
      "heading_deg": 185.0,
      "speed_mps": 156.59065248330364,
      "on_ground": false
    },
    {
      "t": 1782427649,
      "t_rel": 6568.0,
      "lat": 40.4258,
      "lon": -2.866,
      "alt_m": 2743.0,
      "heading_deg": 186.0,
      "speed_mps": 123.48042468382393,
      "on_ground": false
    },
    {
      "t": 1782427650,
      "t_rel": 6569.0,
      "lat": 40.4252,
      "lon": -2.8662,
      "alt_m": 2743.0,
      "heading_deg": 188.0,
      "speed_mps": 68.83137053128782,
      "on_ground": false
    },
    {
      "t": 1782427651,
      "t_rel": 6570.0,
      "lat": 40.4236,
      "lon": -2.8666,
      "alt_m": 2743.0,
      "heading_deg": 189.0,
      "speed_mps": 181.10520945069786,
      "on_ground": false
    },
    {
      "t": 1782427652,
      "t_rel": 6571.0,
      "lat": 40.4226,
      "lon": -2.8669,
      "alt_m": 2743.0,
      "heading_deg": 191.0,
      "speed_mps": 114.05796673046424,
      "on_ground": false
    },
    {
      "t": 1782427653,
      "t_rel": 6572.0,
      "lat": 40.4219,
      "lon": -2.8672,
      "alt_m": 2743.0,
      "heading_deg": 192.0,
      "speed_mps": 81.87452045791355,
      "on_ground": false
    },
    {
      "t": 1782427654,
      "t_rel": 6573.0,
      "lat": 40.4208,
      "lon": -2.8676,
      "alt_m": 2743.0,
      "heading_deg": 194.0,
      "speed_mps": 126.91485353617377,
      "on_ground": false
    },
    {
      "t": 1782427655,
      "t_rel": 6574.0,
      "lat": 40.4196,
      "lon": -2.8681,
      "alt_m": 2743.0,
      "heading_deg": 196.0,
      "speed_mps": 139.98633722981089,
      "on_ground": false
    },
    {
      "t": 1782427656,
      "t_rel": 6575.0,
      "lat": 40.4186,
      "lon": -2.8686,
      "alt_m": 2743.0,
      "heading_deg": 197.0,
      "speed_mps": 118.97872097885333,
      "on_ground": false
    },
    {
      "t": 1782427657,
      "t_rel": 6576.0,
      "lat": 40.4172,
      "lon": -2.8693,
      "alt_m": 2743.0,
      "heading_deg": 199.0,
      "speed_mps": 166.5705853957331,
      "on_ground": false
    },
    {
      "t": 1782427658,
      "t_rel": 6577.0,
      "lat": 40.4162,
      "lon": -2.8699,
      "alt_m": 2743.0,
      "heading_deg": 200.0,
      "speed_mps": 122.2474327836722,
      "on_ground": false
    },
    {
      "t": 1782427659,
      "t_rel": 6578.0,
      "lat": 40.4153,
      "lon": -2.8704,
      "alt_m": 2743.0,
      "heading_deg": 202.0,
      "speed_mps": 108.65953820985011,
      "on_ground": false
    },
    {
      "t": 1782427660,
      "t_rel": 6579.0,
      "lat": 40.4147,
      "lon": -2.8708,
      "alt_m": 2743.0,
      "heading_deg": 204.0,
      "speed_mps": 74.81932601876562,
      "on_ground": false
    },
    {
      "t": 1782427661,
      "t_rel": 6580.0,
      "lat": 40.4134,
      "lon": -2.8717,
      "alt_m": 2743.0,
      "heading_deg": 206.0,
      "speed_mps": 163.40569476819064,
      "on_ground": false
    },
    {
      "t": 1782427662,
      "t_rel": 6581.0,
      "lat": 40.4124,
      "lon": -2.8725,
      "alt_m": 2743.0,
      "heading_deg": 208.0,
      "speed_mps": 130.19875327584535,
      "on_ground": false
    },
    {
      "t": 1782427663,
      "t_rel": 6582.0,
      "lat": 40.4114,
      "lon": -2.8733,
      "alt_m": 2743.0,
      "heading_deg": 209.0,
      "speed_mps": 130.19927687211566,
      "on_ground": false
    },
    {
      "t": 1782427664,
      "t_rel": 6583.0,
      "lat": 40.4105,
      "lon": -2.8741,
      "alt_m": 2743.0,
      "heading_deg": 211.0,
      "speed_mps": 120.8418884274801,
      "on_ground": false
    },
    {
      "t": 1782427665,
      "t_rel": 6584.0,
      "lat": 40.4095,
      "lon": -2.875,
      "alt_m": 2743.0,
      "heading_deg": 213.0,
      "speed_mps": 134.79890529248956,
      "on_ground": false
    },
    {
      "t": 1782427666,
      "t_rel": 6585.0,
      "lat": 40.4086,
      "lon": -2.8759,
      "alt_m": 2743.0,
      "heading_deg": 215.0,
      "speed_mps": 125.78429779699283,
      "on_ground": false
    },
    {
      "t": 1782427667,
      "t_rel": 6586.0,
      "lat": 40.4076,
      "lon": -2.877,
      "alt_m": 2743.0,
      "heading_deg": 217.0,
      "speed_mps": 145.04692009453146,
      "on_ground": false
    },
    {
      "t": 1782427668,
      "t_rel": 6587.0,
      "lat": 40.4069,
      "lon": -2.8779,
      "alt_m": 2743.0,
      "heading_deg": 219.0,
      "speed_mps": 108.92851061638578,
      "on_ground": false
    },
    {
      "t": 1782427669,
      "t_rel": 6588.0,
      "lat": 40.4061,
      "lon": -2.8789,
      "alt_m": 2743.0,
      "heading_deg": 221.0,
      "speed_mps": 122.81018322197629,
      "on_ground": false
    },
    {
      "t": 1782427670,
      "t_rel": 6589.0,
      "lat": 40.4054,
      "lon": -2.8798,
      "alt_m": 2743.0,
      "heading_deg": 223.0,
      "speed_mps": 108.92969868826516,
      "on_ground": false
    },
    {
      "t": 1782427671,
      "t_rel": 6590.0,
      "lat": 40.4045,
      "lon": -2.881,
      "alt_m": 2743.0,
      "heading_deg": 225.0,
      "speed_mps": 142.61553029624167,
      "on_ground": false
    },
    {
      "t": 1782427672,
      "t_rel": 6591.0,
      "lat": 40.4037,
      "lon": -2.8824,
      "alt_m": 2743.0,
      "heading_deg": 226.0,
      "speed_mps": 148.20849345324743,
      "on_ground": false
    },
    {
      "t": 1782427673,
      "t_rel": 6592.0,
      "lat": 40.403,
      "lon": -2.8834,
      "alt_m": 2743.0,
      "heading_deg": 228.0,
      "speed_mps": 115.01463117518693,
      "on_ground": false
    },
    {
      "t": 1782427674,
      "t_rel": 6593.0,
      "lat": 40.4025,
      "lon": -2.8843,
      "alt_m": 2743.0,
      "heading_deg": 229.0,
      "speed_mps": 94.3332502430963,
      "on_ground": false
    },
    {
      "t": 1782427677,
      "t_rel": 6596.0,
      "lat": 40.4003,
      "lon": -2.8879,
      "alt_m": 2743.0,
      "heading_deg": 231.0,
      "speed_mps": 130.28598564158708,
      "on_ground": false
    },
    {
      "t": 1782427723,
      "t_rel": 6642.0,
      "lat": 40.3683,
      "lon": -2.9442,
      "alt_m": 2438.0,
      "heading_deg": 233.0,
      "speed_mps": 129.34348760445224,
      "on_ground": false
    },
    {
      "t": 1782427804,
      "t_rel": 6723.0,
      "lat": 40.3132,
      "lon": -3.0404,
      "alt_m": 1828.0,
      "heading_deg": 233.0,
      "speed_mps": 125.91050036847632,
      "on_ground": false
    },
    {
      "t": 1782427873,
      "t_rel": 6792.0,
      "lat": 40.2672,
      "lon": -3.1212,
      "alt_m": 1828.0,
      "heading_deg": 235.0,
      "speed_mps": 123.93598743538104,
      "on_ground": false
    },
    {
      "t": 1782427875,
      "t_rel": 6794.0,
      "lat": 40.266,
      "lon": -3.1237,
      "alt_m": 1828.0,
      "heading_deg": 237.0,
      "speed_mps": 125.29783272720904,
      "on_ground": false
    },
    {
      "t": 1782427876,
      "t_rel": 6795.0,
      "lat": 40.2654,
      "lon": -3.125,
      "alt_m": 1828.0,
      "heading_deg": 239.0,
      "speed_mps": 128.90981208001256,
      "on_ground": false
    },
    {
      "t": 1782427877,
      "t_rel": 6796.0,
      "lat": 40.2649,
      "lon": -3.1263,
      "alt_m": 1828.0,
      "heading_deg": 240.0,
      "speed_mps": 123.52272347020437,
      "on_ground": false
    },
    {
      "t": 1782427878,
      "t_rel": 6797.0,
      "lat": 40.2644,
      "lon": -3.1277,
      "alt_m": 1828.0,
      "heading_deg": 242.0,
      "speed_mps": 131.1559291314458,
      "on_ground": false
    },
    {
      "t": 1782427879,
      "t_rel": 6798.0,
      "lat": 40.2639,
      "lon": -3.1293,
      "alt_m": 1828.0,
      "heading_deg": 243.0,
      "speed_mps": 146.70304291276912,
      "on_ground": false
    },
    {
      "t": 1782427880,
      "t_rel": 6799.0,
      "lat": 40.2635,
      "lon": -3.1304,
      "alt_m": 1828.0,
      "heading_deg": 245.0,
      "speed_mps": 103.39145817510537,
      "on_ground": false
    },
    {
      "t": 1782427881,
      "t_rel": 6800.0,
      "lat": 40.2631,
      "lon": -3.1318,
      "alt_m": 1828.0,
      "heading_deg": 247.0,
      "speed_mps": 126.84499560013298,
      "on_ground": false
    },
    {
      "t": 1782427882,
      "t_rel": 6801.0,
      "lat": 40.2628,
      "lon": -3.1331,
      "alt_m": 1828.0,
      "heading_deg": 248.0,
      "speed_mps": 115.24046484575015,
      "on_ground": false
    },
    {
      "t": 1782427883,
      "t_rel": 6802.0,
      "lat": 40.2624,
      "lon": -3.1346,
      "alt_m": 1828.0,
      "heading_deg": 250.0,
      "speed_mps": 134.82542011700298,
      "on_ground": false
    },
    {
      "t": 1782427884,
      "t_rel": 6803.0,
      "lat": 40.2621,
      "lon": -3.1359,
      "alt_m": 1828.0,
      "heading_deg": 251.0,
      "speed_mps": 115.24155736630414,
      "on_ground": false
    },
    {
      "t": 1782427885,
      "t_rel": 6804.0,
      "lat": 40.2618,
      "lon": -3.1372,
      "alt_m": 1828.0,
      "heading_deg": 253.0,
      "speed_mps": 115.24202558463551,
      "on_ground": false
    },
    {
      "t": 1782427886,
      "t_rel": 6805.0,
      "lat": 40.2614,
      "lon": -3.1396,
      "alt_m": 1828.0,
      "heading_deg": 255.0,
      "speed_mps": 208.44784057407153,
      "on_ground": false
    },
    {
      "t": 1782427887,
      "t_rel": 6806.0,
      "lat": 40.2613,
      "lon": -3.1403,
      "alt_m": 1828.0,
      "heading_deg": 257.0,
      "speed_mps": 60.42919209853334,
      "on_ground": false
    },
    {
      "t": 1782427888,
      "t_rel": 6807.0,
      "lat": 40.261,
      "lon": -3.1425,
      "alt_m": 1828.0,
      "heading_deg": 258.0,
      "speed_mps": 189.63499174448185,
      "on_ground": false
    },
    {
      "t": 1782427889,
      "t_rel": 6808.0,
      "lat": 40.2609,
      "lon": -3.144,
      "alt_m": 1828.0,
      "heading_deg": 260.0,
      "speed_mps": 127.76555627438829,
      "on_ground": false
    },
    {
      "t": 1782427890,
      "t_rel": 6809.0,
      "lat": 40.2608,
      "lon": -3.1455,
      "alt_m": 1828.0,
      "heading_deg": 262.0,
      "speed_mps": 127.76574369436518,
      "on_ground": false
    },
    {
      "t": 1782427891,
      "t_rel": 6810.0,
      "lat": 40.2608,
      "lon": -3.1469,
      "alt_m": 1828.0,
      "heading_deg": 264.0,
      "speed_mps": 118.79564813858181,
      "on_ground": false
    },
    {
      "t": 1782427892,
      "t_rel": 6811.0,
      "lat": 40.2608,
      "lon": -3.1484,
      "alt_m": 1828.0,
      "heading_deg": 266.0,
      "speed_mps": 127.28105157687511,
      "on_ground": false
    },
    {
      "t": 1782427893,
      "t_rel": 6812.0,
      "lat": 40.2608,
      "lon": -3.15,
      "alt_m": 1828.0,
      "heading_deg": 267.0,
      "speed_mps": 135.7664550150902,
      "on_ground": false
    },
    {
      "t": 1782427894,
      "t_rel": 6813.0,
      "lat": 40.2608,
      "lon": -3.1515,
      "alt_m": 1828.0,
      "heading_deg": 270.0,
      "speed_mps": 127.28105157687511,
      "on_ground": false
    },
    {
      "t": 1782427895,
      "t_rel": 6814.0,
      "lat": 40.2609,
      "lon": -3.153,
      "alt_m": 1828.0,
      "heading_deg": 271.0,
      "speed_mps": 127.76574369436518,
      "on_ground": false
    },
    {
      "t": 1782427896,
      "t_rel": 6815.0,
      "lat": 40.261,
      "lon": -3.1548,
      "alt_m": 1828.0,
      "heading_deg": 273.0,
      "speed_mps": 153.14114679328893,
      "on_ground": false
    },
    {
      "t": 1782427898,
      "t_rel": 6817.0,
      "lat": 40.2613,
      "lon": -3.1577,
      "alt_m": 1828.0,
      "heading_deg": 275.0,
      "speed_mps": 124.16310206983182,
      "on_ground": false
    },
    {
      "t": 1782427901,
      "t_rel": 6820.0,
      "lat": 40.2618,
      "lon": -3.1625,
      "alt_m": 1828.0,
      "heading_deg": 277.0,
      "speed_mps": 137.02399326287852,
      "on_ground": false
    },
    {
      "t": 1782427948,
      "t_rel": 6867.0,
      "lat": 40.2717,
      "lon": -3.2345,
      "alt_m": 1828.0,
      "heading_deg": 279.0,
      "speed_mps": 132.07117070158694,
      "on_ground": false
    },
    {
      "t": 1782428002,
      "t_rel": 6921.0,
      "lat": 40.282,
      "lon": -3.3133,
      "alt_m": 1828.0,
      "heading_deg": 280.0,
      "speed_mps": 125.59838485528013,
      "on_ground": false
    },
    {
      "t": 1782428004,
      "t_rel": 6923.0,
      "lat": 40.2826,
      "lon": -3.3162,
      "alt_m": 1524.0,
      "heading_deg": 283.0,
      "speed_mps": 127.4425411151018,
      "on_ground": false
    },
    {
      "t": 1782428005,
      "t_rel": 6924.0,
      "lat": 40.2829,
      "lon": -3.3174,
      "alt_m": 1524.0,
      "heading_deg": 284.0,
      "speed_mps": 107.11843026248616,
      "on_ground": false
    },
    {
      "t": 1782428006,
      "t_rel": 6925.0,
      "lat": 40.2832,
      "lon": -3.319,
      "alt_m": 1524.0,
      "heading_deg": 286.0,
      "speed_mps": 139.76120182889153,
      "on_ground": false
    },
    {
      "t": 1782428007,
      "t_rel": 6926.0,
      "lat": 40.2836,
      "lon": -3.3202,
      "alt_m": 1524.0,
      "heading_deg": 287.0,
      "speed_mps": 111.08402525364124,
      "on_ground": false
    },
    {
      "t": 1782428008,
      "t_rel": 6927.0,
      "lat": 40.284,
      "lon": -3.3216,
      "alt_m": 1524.0,
      "heading_deg": 289.0,
      "speed_mps": 126.81127665995525,
      "on_ground": false
    },
    {
      "t": 1782428009,
      "t_rel": 6928.0,
      "lat": 40.2845,
      "lon": -3.3231,
      "alt_m": 1524.0,
      "heading_deg": 291.0,
      "speed_mps": 138.85356552021645,
      "on_ground": false
    },
    {
      "t": 1782428010,
      "t_rel": 6929.0,
      "lat": 40.285,
      "lon": -3.3242,
      "alt_m": 1524.0,
      "heading_deg": 293.0,
      "speed_mps": 108.61473109901115,
      "on_ground": false
    },
    {
      "t": 1782428011,
      "t_rel": 6930.0,
      "lat": 40.2854,
      "lon": -3.3254,
      "alt_m": 1524.0,
      "heading_deg": 294.0,
      "speed_mps": 111.08154157794614,
      "on_ground": false
    },
    {
      "t": 1782428012,
      "t_rel": 6931.0,
      "lat": 40.286,
      "lon": -3.3268,
      "alt_m": 1524.0,
      "heading_deg": 296.0,
      "speed_mps": 136.21001967415464,
      "on_ground": false
    },
    {
      "t": 1782428013,
      "t_rel": 6932.0,
      "lat": 40.2866,
      "lon": -3.3281,
      "alt_m": 1524.0,
      "heading_deg": 298.0,
      "speed_mps": 128.88106444295389,
      "on_ground": false
    },
    {
      "t": 1782428014,
      "t_rel": 6933.0,
      "lat": 40.2872,
      "lon": -3.3293,
      "alt_m": 1524.0,
      "heading_deg": 300.0,
      "speed_mps": 121.7023010614073,
      "on_ground": false
    },
    {
      "t": 1782428015,
      "t_rel": 6934.0,
      "lat": 40.2878,
      "lon": -3.3306,
      "alt_m": 1524.0,
      "heading_deg": 301.0,
      "speed_mps": 128.87938951971265,
      "on_ground": false
    },
    {
      "t": 1782428016,
      "t_rel": 6935.0,
      "lat": 40.2886,
      "lon": -3.3319,
      "alt_m": 1524.0,
      "heading_deg": 303.0,
      "speed_mps": 141.67445951459968,
      "on_ground": false
    },
    {
      "t": 1782428017,
      "t_rel": 6936.0,
      "lat": 40.2891,
      "lon": -3.333,
      "alt_m": 1524.0,
      "heading_deg": 304.0,
      "speed_mps": 108.60986923047496,
      "on_ground": false
    },
    {
      "t": 1782428018,
      "t_rel": 6937.0,
      "lat": 40.2899,
      "lon": -3.3343,
      "alt_m": 1524.0,
      "heading_deg": 306.0,
      "speed_mps": 141.67280884867,
      "on_ground": false
    },
    {
      "t": 1782428022,
      "t_rel": 6941.0,
      "lat": 40.2926,
      "lon": -3.3388,
      "alt_m": 1524.0,
      "heading_deg": 308.0,
      "speed_mps": 121.40036253122331,
      "on_ground": false
    },
    {
      "t": 1782428047,
      "t_rel": 6966.0,
      "lat": 40.3101,
      "lon": -3.3663,
      "alt_m": 1524.0,
      "heading_deg": 310.0,
      "speed_mps": 121.49204993263749,
      "on_ground": false
    },
    {
      "t": 1782428052,
      "t_rel": 6971.0,
      "lat": 40.3138,
      "lon": -3.3716,
      "alt_m": 1524.0,
      "heading_deg": 312.0,
      "speed_mps": 121.85489309361355,
      "on_ground": false
    },
    {
      "t": 1782428057,
      "t_rel": 6976.0,
      "lat": 40.3176,
      "lon": -3.3766,
      "alt_m": 1524.0,
      "heading_deg": 315.0,
      "speed_mps": 119.70858849118727,
      "on_ground": false
    },
    {
      "t": 1782428062,
      "t_rel": 6981.0,
      "lat": 40.3215,
      "lon": -3.3814,
      "alt_m": 1524.0,
      "heading_deg": 317.0,
      "speed_mps": 118.939612965941,
      "on_ground": false
    },
    {
      "t": 1782428069,
      "t_rel": 6988.0,
      "lat": 40.3271,
      "lon": -3.3877,
      "alt_m": 1524.0,
      "heading_deg": 319.0,
      "speed_mps": 117.19375930787008,
      "on_ground": false
    },
    {
      "t": 1782428086,
      "t_rel": 7005.0,
      "lat": 40.3412,
      "lon": -3.4021,
      "alt_m": 1219.0,
      "heading_deg": 322.0,
      "speed_mps": 116.87904618383462,
      "on_ground": false
    },
    {
      "t": 1782428133,
      "t_rel": 7052.0,
      "lat": 40.3786,
      "lon": -3.44,
      "alt_m": 914.0,
      "heading_deg": 322.0,
      "speed_mps": 111.79194993957263,
      "on_ground": false
    },
    {
      "t": 1782428197,
      "t_rel": 7116.0,
      "lat": 40.4203,
      "lon": -3.4821,
      "alt_m": 609.0,
      "heading_deg": 322.0,
      "speed_mps": 91.3889767396856,
      "on_ground": false
    },
    {
      "t": 1782428273,
      "t_rel": 7192.0,
      "lat": 40.4642,
      "lon": -3.5266,
      "alt_m": 609.0,
      "heading_deg": 322.0,
      "speed_mps": 81.12171505941201,
      "on_ground": false
    }
  ],
  "stats": {
    "num_waypoints": 425,
    "duration_s": 7192,
    "distance_km": 1509.321,
    "max_alt_m": 10668.0,
    "max_speed_mps": 353.9005161837405
  }
}